Workbook
Name Zone: #REF!

Sheet Sales
A1: Date | B1: 12:27 AM | C1: Quarter | D1: Locations | E1: Platforms | F1: Fullfilled_By | G1: Product Name | H1: Product Type | I1: Product_ID | J1: Orders | K1: Order_Type | L1: Sales_Volume | M1: Sales_Revenue | N1: Payout
A2: 45666 | B2: 0.76388889 | C2: ="Q" & CHOOSE(MONTH(Sales!$A2), "1", "1", "1", "2", "2", "2", "3", "3", "3", "4", "4", "4") & "_" & YEAR(Sales!$A2) -> Q1_2025 | D2: N/A | E2: Amazon | F2: MFN | G2: Zody Diaper | H2: Single | I2: ZODY DIAPER - NVYBLU | J2: 1 | K2: Review Purchase | L2: 1 | M2: 299 | N2: 0
A3: 45668 | B3: 0.74722222 | C3: ="Q" & CHOOSE(MONTH(Sales!$A3), "1", "1", "1", "2", "2", "2", "3", "3", "3", "4", "4", "4") & "_" & YEAR(Sales!$A3) -> Q1_2025 | D3: N/A | E3: Amazon | F3: MFN | G3: Zody Diaper | H3: Bundle | I3: ZODY DIAPER-2PCS-MC1+MC2 | J3: 1 | K3: Review Purchase | L3: 2 | M3: 598 | N3: 0
A4: 45670 | B4: 45670.656 | C4: ="Q" & CHOOSE(MONTH(Sales!$A4), "1", "1", "1", "2", "2", "2", "3", "3", "3", "4", "4", "4") & "_" & YEAR(Sales!$A4) -> Q1_2025 | D4: N/A | E4: Amazon | F4: MFN | G4: Zody Diaper | H4: Single | I4: ZODY DIAPER - NVYBLU | J4: 1 | K4: Organic | L4: 1 | M4: 295 | N4: 0
A5: 45671 | B5: 0.72708333 | C5: ="Q" & CHOOSE(MONTH(Sales!$A5), "1", "1", "1", "2", "2", "2", "3", "3", "3", "4", "4", "4") & "_" & YEAR(Sales!$A5) -> Q1_2025 | D5: N/A | E5: Amazon | F5: MFN | G5: Zody Diaper | H5: Single | I5: ZODY DIAPER - NVYBLU | J5: 1 | K5: Review Purchase | L5: 1 | M5: 289 | N5: 0
A6: 45671 | B6: 0.97777778 | C6: ="Q" & CHOOSE(MONTH(Sales!$A6), "1", "1", "1", "2", "2", "2", "3", "3", "3", "4", "4", "4") & "_" & YEAR(Sales!$A6) -> Q1_2025 | D6: N/A | E6: Amazon | F6: MFN | G6: Zody Diaper | H6: Single | I6: ZODY DIAPER - NVYBLU | J6: 1 | K6: Organic | L6: 1 | M6: 284 | N6: 0
A7: 45671 | B7: 0.97777778 | C7: ="Q" & CHOOSE(MONTH(Sales!$A7), "1", "1", "1", "2", "2", "2", "3", "3", "3", "4", "4", "4") & "_" & YEAR(Sales!$A7) -> Q1_2025 | D7: N/A | E7: Amazon | F7: MFN | G7: Zody Diaper | H7: Single | I7: ZODY DIAPER-MC5 | J7: 1 | K7: Organic | L7: 1 | M7: 299 | N7: 0
A8: 45677 | B8: 0.98263889 | C8: ="Q" & CHOOSE(MONTH(Sales!$A8), "1", "1", "1", "2", "2", "2", "3", "3", "3", "4", "4", "4") & "_" & YEAR(Sales!$A8) -> Q1_2025 | D8: N/A | E8: Amazon | F8: MFN | G8: Diaper Pad | H8: Bundle | I8: DIAPER PAD-3PCS | J8: 1 | K8: Organic | L8: 3 | M8: 199 | N8: 0
A9: 45677 | B9: 0.53263889 | C9: ="Q" & CHOOSE(MONTH(Sales!$A9), "1", "1", "1", "2", "2", "2", "3", "3", "3", "4", "4", "4") & "_" & YEAR(Sales!$A9) -> Q1_2025 | D9: N/A | E9: Amazon | F9: MFN | G9: Diaper Pad | H9: Bundle | I9: DIAPER PAD-6PCS | J9: 2 | K9: Organic | L9: 12 | M9: 798 | N9: 0
A10: 45678 | B10: 0.69375 | C10: ="Q" & CHOOSE(MONTH(Sales!$A10), "1", "1", "1", "2", "2", "2", "3", "3", "3", "4", "4", "4") & "_" & YEAR(Sales!$A10) -> Q1_2025 | D10: N/A | E10: Amazon | F10: MFN | G10: Zody Diaper | H10: Single | I10: ZODY DIAPER-MC7 | J10: 1 | K10: Organic | L10: 1 | M10: 249 | N10: 0
A11: 45678 | B11: 0.94652778 | C11: ="Q" & CHOOSE(MONTH(Sales!$A11), "1", "1", "1", "2", "2", "2", "3", "3", "3", "4", "4", "4") & "_" & YEAR(Sales!$A11) -> Q1_2025 | D11: N/A | E11: Amazon | F11: MFN | G11: Diaper Pad | H11: Bundle | I11: DIAPER PAD-3PCS | J11: 1 | K11: Organic | L11: 3 | M11: 249 | N11: 0
A12: 45679 | B12: 0.47430556 | C12: ="Q" & CHOOSE(MONTH(Sales!$A12), "1", "1", "1", "2", "2", "2", "3", "3", "3", "4", "4", "4") & "_" & YEAR(Sales!$A12) -> Q1_2025 | D12: N/A | E12: Amazon | F12: MFN | G12: Zody Diaper | H12: Single | I12: ZODY DIAPER - NVYBLU | J12: 1 | K12: Organic | L12: 1 | M12: 249 | N12: 0
A13: 45681 | B13: 0.029861111 | C13: ="Q" & CHOOSE(MONTH(Sales!$A13), "1", "1", "1", "2", "2", "2", "3", "3", "3", "4", "4", "4") & "_" & YEAR(Sales!$A13) -> Q1_2025 | D13: N/A | E13: Amazon | F13: MFN | G13: Zody Diaper | H13: Single | I13: ZODY DIAPER-MC5 | J13: 1 | K13: Organic | L13: 1 | M13: 259 | N13: 0
... A63: 45697 | B63: 0.64513889 | C63: ="Q" & CHOOSE(MONTH(Sales!$A63), "1", "1", "1", "2", "2", "2", "3", "3", "3", "4", "4", "4") & "_" & YEAR(Sales!$A63) -> Q1_2025 | D63: Tamil Nadu | E63: Amazon | F63: MFN | G63: Zody Diaper | H63: Single | I63: ZODY DIAPER-MC3 | J63: 1 | K63: Organic | L63: 1 | M63: 289 | N63: 0
A64: 45697 | B64: 8:19 pm | C64: ="Q" & CHOOSE(MONTH(Sales!$A64), "1", "1", "1", "2", "2", "2", "3", "3", "3", "4", "4", "4") & "_" & YEAR(Sales!$A64) -> Q1_2025 | D64: Maharashtra | E64: Amazon | F64: MFN | G64: Jabala Wings | H64: Bundle | I64: JABALA WINGS-5PCS- 0-3M-S1 | J64: 1 | K64: Organic | L64: 5 | M64: 299 | N64: 0
A65: 45697 | B65: 0.92638889 | C65: ="Q" & CHOOSE(MONTH(Sales!$A65), "1", "1", "1", "2", "2", "2", "3", "3", "3", "4", "4", "4") & "_" & YEAR(Sales!$A65) -> Q1_2025 | D65: Uttar Pradesh | E65: Amazon | F65: MFN | G65: Zody Diaper | H65: Bundle | I65: ZODY DIAPER-5PCS | J65: 1 | K65: Organic | L65: 5 | M65: 1190 | N65: 0
A66: 45697 | B66: 0.92638889 | C66: ="Q" & CHOOSE(MONTH(Sales!$A66), "1", "1", "1", "2", "2", "2", "3", "3", "3", "4", "4", "4") & "_" & YEAR(Sales!$A66) -> Q1_2025 | D66: Uttar Pradesh | E66: Amazon | F66: MFN | G66: Zody Diaper | H66: Bundle | I66: DIAPER PAD-3PCS | J66: 1 | K66: Free | L66: 3 | M66: 0 | N66: 0
A67: 45698 | B67: 0.60208333 | C67: ="Q" & CHOOSE(MONTH(Sales!$A67), "1", "1", "1", "2", "2", "2", "3", "3", "3", "4", "4", "4") & "_" & YEAR(Sales!$A67) -> Q1_2025 | D67: Tamil Nadu | E67: Amazon | F67: MFN | G67: Jabala Mist | H67: Bundle | I67: JABALA MIST-5PCS- 0-3M | J67: 1 | K67: Organic | L67: 5 | M67: 374 | N67: 0
A68: 45698 | B68: 0.98402778 | C68: ="Q" & CHOOSE(MONTH(Sales!$A68), "1", "1", "1", "2", "2", "2", "3", "3", "3", "4", "4", "4") & "_" & YEAR(Sales!$A68) -> Q1_2025 | D68: Gujarat | E68: Amazon | F68: MFN | G68: Jabala Wings | H68: Bundle | I68: JABALA WINGS-3PCS- 0-3M-S2 | J68: 1 | K68: Organic | L68: 3 | M68: 199 | N68: 0
A69: 45699 | B69: 0.5125 | C69: ="Q" & CHOOSE(MONTH(Sales!$A69), "1", "1", "1", "2", "2", "2", "3", "3", "3", "4", "4", "4") & "_" & YEAR(Sales!$A69) -> Q1_2025 | D69: Telangana | E69: Amazon | F69: MFN | G69: Jabala Wings | H69: Bundle | I69: JABALA WINGS-3PCS- 0-3M-S2 | J69: 1 | K69: Organic | L69: 5 | M69: 299 | N69: 0
A70: 45699 | B70: 0.54583333 | C70: ="Q" & CHOOSE(MONTH(Sales!$A70), "1", "1", "1", "2", "2", "2", "3", "3", "3", "4", "4", "4") & "_" & YEAR(Sales!$A70) -> Q1_2025 | D70: Uttar Pradesh | E70: Amazon | F70: MFN | G70: Zody Diaper | H70: Single | I70: ZODY DIAPER - NVYBLU | J70: 1 | K70: Organic | L70: 1 | M70: 284 | N70: 0
A71: 45699 | B71: 0.72638889 | C71: ="Q" & CHOOSE(MONTH(Sales!$A71), "1", "1", "1", "2", "2", "2", "3", "3", "3", "4", "4", "4") & "_" & YEAR(Sales!$A71) -> Q1_2025 | D71: Kerala | E71: Amazon | F71: MFN | G71: Diaper Pad | H71: Bundle | I71: DIAPER PAD-3PCS | J71: 1 | K71: Organic | L71: 3 | M71: 269 | N71: 0
A72: 45699 | B72: 0.90069444 | C72: ="Q" & CHOOSE(MONTH(Sales!$A72), "1", "1", "1", "2", "2", "2", "3", "3", "3", "4", "4", "4") & "_" & YEAR(Sales!$A72) -> Q1_2025 | D72: Andhra Pradesh | E72: Amazon | F72: MFN | G72: Jabala Wings | H72: Bundle | I72: JABALA WINGS-3PCS- 3-6M-S2 | J72: 1 | K72: Organic | L72: 3 | M72: 199 | N72: 0
A73: 45699 | B73: 0.97152778 | C73: ="Q" & CHOOSE(MONTH(Sales!$A73), "1", "1", "1", "2", "2", "2", "3", "3", "3", "4", "4", "4") & "_" & YEAR(Sales!$A73) -> Q1_2025 | D73: Gujarat | E73: Amazon | F73: MFN | G73: Jabala Wings | H73: Bundle | I73: JABALA WINGS-5PCS- 0-3M-S1 | J73: 1 | K73: Organic | L73: 5 | M73: 299 | N73: 0
A74: 45700 | B74: 0.51319444 | C74: ="Q" & CHOOSE(MONTH(Sales!$A74), "1", "1", "1", "2", "2", "2", "3", "3", "3", "4", "4", "4") & "_" & YEAR(Sales!$A74) -> Q1_2025 | D74: Kerala | E74: Amazon | F74: MFN | G74: Diaper Pad | H74: Bundle | I74: DIAPER PAD-3PCS | J74: 1 | K74: Organic | L74: 3 | M74: 285 | N74: 0
A75: 45700 | B75: 0.60972222 | C75: ="Q" & CHOOSE(MONTH(Sales!$A75), "1", "1", "1", "2", "2", "2", "3", "3", "3", "4", "4", "4") & "_" & YEAR(Sales!$A75) -> Q1_2025 | D75: Karnataka | E75: Amazon | F75: MFN | G75: Diaper Pad | H75: Bundle | I75: DIAPER PAD-3PCS | J75: 1 | K75: Organic | L75: 3 | M75: 285 | N75: 0
A76: 45700 | B76: 0.96319444 | C76: ="Q" & CHOOSE(MONTH(Sales!$A76), "1", "1", "1", "2", "2", "2", "3", "3", "3", "4", "4", "4") & "_" & YEAR(Sales!$A76) -> Q1_2025 | D76: Madhya Pradesh | E76: Amazon | F76: MFN | G76: Jabala Wings | H76: Bundle | I76: JABALA WINGS-3PCS-S1 | J76: 1 | K76: Organic | L76: 3 | M76: 199 | N76: 87.34
... A80: 45701 | B80: 0.86458333 | C80: ="Q" & CHOOSE(MONTH(Sales!$A80), "1", "1", "1", "2", "2", "2", "3", "3", "3", "4", "4", "4") & "_" & YEAR(Sales!$A80) -> Q1_2025 | D80: Maharashtra | E80: Amazon | F80: MFN | G80: Zody Diaper | H80: Bundle | I80: ZODY DIAPER-2PCS | J80: 1 | K80: Organic | L80: 2 | M80: 579 | N80: 378
A81: 45702 | B81: 0.34861111 | C81: Q1_2025 | D81: Delhi | E81: Amazon | F81: MFN | G81: Diaper Pad | H81: Bundle | I81: DIAPER PAD-3PCS | J81: 1 | K81: Organic | L81: 3 | M81: 287 | N81: 165
A82: 45702 | B82: 0.37430556 | C82: Q1_2025 | D82: Odisha | E82: Amazon | F82: MFN | G82: Diaper Pad | H82: Bundle | I82: DIAPER PAD-3PCS | J82: 1 | K82: Organic | L82: 3 | M82: 282 | N82: 161
A83: 45702 | B83: 0.52708333 | C83: Q1_2025 | D83: Kerala | E83: Amazon | F83: MFN | G83: Diaper Pad | H83: Bundle | I83: DIAPER PAD-3PCS | J83: 1 | K83: Organic | L83: 3 | M83: 288 | N83: 166
A84: 45702 | B84: 0.88819444 | C84: Q1_2025 | D84: Telangana | E84: Amazon | F84: MFN | G84: Diaper Pad | H84: Bundle | I84: DIAPER PAD-5PCS | J84: 1 | K84: Organic | L84: 5 | M84: 429 | N84: 292
A85: 45703 | B85: 0.039583333 | C85: Q1_2025 | D85: Madhya Pradesh | E85: Amazon | F85: MFN | G85: Jabala Wings | H85: Bundle | I85: JABALA WINGS-3PCS- 0-3M-S2 | J85: 1 | K85: Organic | L85: 3 | M85: 199 | N85: 87.34
A86: 45703 | B86: 0.42916667 | C86: Q1_2025 | D86: Karnataka | E86: Amazon | F86: MFN | G86: Jabala Wings | H86: Bundle | I86: JABALA WINGS-3PCS- 0-3M-S2 | J86: 1 | K86: Organic | L86: 3 | M86: 199 | N86: 87.34
A87: 45703 | B87: 0.4375 | C87: Q1_2025 | D87: Kerala | E87: Amazon | F87: MFN | G87: Diaper Pad | H87: Bundle | I87: DIAPER PAD-5PCS | J87: 1 | K87: Organic | L87: 5 | M87: 439 | N87: 302
A88: 45703 | B88: 0.51527778 | C88: Q1_2025 | D88: Maharashtra | E88: Amazon | F88: MFN | G88: Diaper Pad | H88: Bundle | I88: DIAPER PAD-3PCS | J88: 1 | K88: Organic | L88: 3 | M88: 289 | N88: 167
A89: 45703 | B89: 0.53263889 | C89: Q1_2025 | D89: Kerala | E89: Amazon | F89: MFN | G89: Diaper Pad | H89: Bundle | I89: DIAPER PAD-3PCS | J89: 2 | K89: Organic | L89: 6 | M89: 560.66 | N89: 362.84
A90: 45703 | B90: 0.55555556 | C90: Q1_2025 | D90: Maharashtra | E90: Amazon | F90: MFN | G90: Jabala Wings | H90: Bundle | I90: JABALA WINGS-3PCS- 3-6M-S2 | J90: 1 | K90: Organic | L90: 3 | M90: 199 | N90: 87.34
A91: 45703 | B91: 0.55625 | C91: Q1_2025 | D91: Haryana | E91: Amazon | F91: MFN | G91: Jabala Wings | H91: Bundle | I91: JABALA WINGS-6PCS- 3-6M-S2 | J91: 1 | K91: Organic | L91: 6 | M91: 344 | N91: 206
A92: 45703 | B92: 0.83611111 | C92: Q1_2025 | D92: Manipur | E92: Amazon | F92: MFN | G92: Diaper Pad | H92: Bundle | I92: DIAPER PAD-3PCS | J92: 1 | K92: Organic | L92: 3 | M92: 284 | N92: 163
... A169: 45713 | B169: 0.7875 | C169: Q1_2025 | D169: Tamil Nadu | E169: Amazon | F169: MFN | G169: Diaper Pad | H169: Bundle | I169: DIAPER PAD-3PCS | J169: 1 | K169: Organic | L169: 3 | M169: 490 | N169: 490
A170: 45713 | B170: 0.7875 | C170: ="Q" & CHOOSE(MONTH(Sales!$A170), "1", "1", "1", "2", "2", "2", "3", "3", "3", "4", "4", "4") & "_" & YEAR(Sales!$A170) -> Q1_2025 | D170: Tamil Nadu | E170: Amazon | F170: MFN | G170: Zody Diaper | H170: Bundle | I170: ZODY DIAPER - NVYBLU | J170: 1 | K170: Free | L170: 1 | M170: 0 | N170: 0
A171: 45713 | B171: 0.84166667 | C171: Q1_2025 | D171: Maharashtra | E171: Amazon | F171: MFN | G171: Diaper Pad | H171: Bundle | I171: ZODY DIAPER-5PCS | J171: 1 | K171: Organic | L171: 5 | M171: 489 | N171: 349
A172: 45713 | B172: 0.84930556 | C172: Q1_2025 | D172: Andhra Pradesh | E172: Amazon | F172: MFN | G172: Diaper Pad | H172: Bundle | I172: DIAPER PAD-5PCS | J172: 2 | K172: Organic | L172: 10 | M172: 948 | N172: 700
A173: 45713 | B173: 0.85972222 | C173: Q1_2025 | D173: West Bengal | E173: Amazon | F173: MFN | G173: Diaper Pad | H173: Bundle | I173: DIAPER PAD-3PCS | J173: 1 | K173: Organic | L173: 3 | M173: 348 | N173: 219
A174: 45713 | B174: 0.89375 | C174: Q1_2025 | D174: Karnataka | E174: Amazon | F174: MFN | G174: Window Cradle Stand | H174: Single | I174: WND CRADLE STAND-1M-GRP | J174: 1 | K174: Organic | L174: 1 | M174: 699 | N174: 483
A175: 45713 | B175: 0.99166667 | C175: Q1_2025 | D175: Rajasthan | E175: Amazon | F175: MFN | G175: Jabala Wings | H175: Bundle | I175: JABALA WINGS-5PCS- 0-3M-S1 | J175: 1 | K175: Organic | L175: 5 | M175: 325 | N175: 199
A176: 45714 | B176: 0.073611111 | C176: Q1_2025 | D176: Maharashtra | E176: Amazon | F176: MFN | G176: Diaper Pad | H176: Bundle | I176: DIAPER PAD-3PCS | J176: 1 | K176: Organic | L176: 3 | M176: 349 | N176: 220
A177: 45714 | B177: 0.41527778 | C177: Q1_2025 | D177: Tamil Nadu | E177: Amazon | F177: MFN | G177: Diaper Pad | H177: Bundle | I177: DIAPER PAD-3PCS | J177: 1 | K177: Organic | L177: 3 | M177: 349 | N177: 220
A178: 45714 | B178: 0.49236111 | C178: Q1_2025 | D178: Kerala | E178: Amazon | F178: MFN | G178: Diaper Pad | H178: Bundle | I178: DIAPER PAD-5PCS | J178: 1 | K178: Organic | L178: 5 | M178: 489 | N178: 349
A179: 45714 | B179: 0.58333333 | C179: Q1_2025 | D179: Karnataka | E179: Amazon | F179: MFN | G179: Diaper Pad | H179: Bundle | I179: DIAPER PAD-3PCS | J179: 1 | K179: Organic | L179: 3 | M179: 359 | N179: 239
A180: 45714 | B180: 0.71875 | C180: Q1_2025 | D180: Telangana | E180: Amazon | F180: MFN | G180: Diaper Pad | H180: Bundle | I180: DIAPER PAD-3PCS | J180: 1 | K180: Organic | L180: 3 | M180: 359 | N180: 239
A181: 45714 | B181: 0.73333333 | C181: Q1_2025 | D181: Karnataka | E181: Amazon | F181: MFN | G181: Window Cradle Stand | H181: Single | I181: WND CRADLE STAND-1M-GRP | J181: 1 | K181: Organic | L181: 1 | M181: 685 | N181: 426
A182: 45714 | B182: 0.80277778 | C182: Q1_2025 | D182: Karnataka | E182: Amazon | F182: MFN | G182: Feeding Bed | H182: Single | I182: FEEDING BED-PNK&WT | J182: 1 | K182: Organic | L182: 1 | M182: 759 | N182: 508
... A200: 45716 | B200: 0.96527778 | C200: Q1_2025 | D200: Maharashtra | E200: Amazon | F200: MFN | G200: Zody Diaper | H200: Single | I200: ZODY DIAPER-MC7 | J200: 1 | K200: Organic | L200: 1 | M200: 0 | N200: 0
A201: 45717 | B201: 0.097916667 | C201: ="Q" & CHOOSE(MONTH(Sales!$A201), "1", "1", "1", "2", "2", "2", "3", "3", "3", "4", "4", "4") & "_" & YEAR(Sales!$A201) -> Q1_2025 | D201: Telangana | E201: Amazon | F201: MFN | G201: Jabala Wings | H201: Bundle | I201: JABALA WINGS-5PCS- 3-6M-S1 | J201: 1 | K201: Organic | L201: 5 | M201: 329 | N201: 193
A202: 45717 | B202: 0.10208333 | C202: ="Q" & CHOOSE(MONTH(Sales!$A202), "1", "1", "1", "2", "2", "2", "3", "3", "3", "4", "4", "4") & "_" & YEAR(Sales!$A202) -> Q1_2025 | D202: Odisha | E202: Amazon | F202: MFN | G202: Diaper Pad | H202: Bundle | I202: DIAPER PAD-3PCS | J202: 1 | K202: Organic | L202: 3 | M202: 359 | N202: 239
A203: 45717 | B203: 0.37708333 | C203: ="Q" & CHOOSE(MONTH(Sales!$A203), "1", "1", "1", "2", "2", "2", "3", "3", "3", "4", "4", "4") & "_" & YEAR(Sales!$A203) -> Q1_2025 | D203: Tamil Nadu | E203: Amazon | F203: MFN | G203: Window Cradle Stand | H203: Single | I203: WND CRADLE STAND-1M-GRP | J203: 1 | K203: Organic | L203: 1 | M203: 739 | N203: 470
A204: 45717 | B204: 0.38055556 | C204: ="Q" & CHOOSE(MONTH(Sales!$A204), "1", "1", "1", "2", "2", "2", "3", "3", "3", "4", "4", "4") & "_" & YEAR(Sales!$A204) -> Q1_2025 | D204: West Bengal | E204: Amazon | F204: MFN | G204: Jabala Wings | H204: Bundle | I204: JABALA WINGS-3PCS- 3-6M-S1 | J204: 1 | K204: Organic | L204: 3 | M204: 209 | N204: 96
A205: 45717 | B205: 0.50694444 | C205: ="Q" & CHOOSE(MONTH(Sales!$A205), "1", "1", "1", "2", "2", "2", "3", "3", "3", "4", "4", "4") & "_" & YEAR(Sales!$A205) -> Q1_2025 | D205: Gujarat | E205: Amazon | F205: MFN | G205: Jabala Wings | H205: Bundle | I205: JABALA WINGS-6PCS- 3-6M-S2 | J205: 1 | K205: Organic | L205: 6 | M205: 389 | N205: 246
A206: 45717 | B206: 0.52222222 | C206: ="Q" & CHOOSE(MONTH(Sales!$A206), "1", "1", "1", "2", "2", "2", "3", "3", "3", "4", "4", "4") & "_" & YEAR(Sales!$A206) -> Q1_2025 | D206: Haryana | E206: Amazon | F206: MFN | G206: Zody Diaper | H206: Bundle | I206: ZODY DIAPER-5PCS | J206: 1 | K206: Organic | L206: 5 | M206: 1289 | N206: 809
A207: 45717 | B207: 0.52430556 | C207: ="Q" & CHOOSE(MONTH(Sales!$A207), "1", "1", "1", "2", "2", "2", "3", "3", "3", "4", "4", "4") & "_" & YEAR(Sales!$A207) -> Q1_2025 | D207: Tamil Nadu | E207: Amazon | F207: MFN | G207: Diaper Pad | H207: Bundle | I207: DIAPER PAD-5PCS | J207: 1 | K207: Organic | L207: 5 | M207: 509 | N207: 317
A208: 45717 | B208: 0.71041667 | C208: ="Q" & CHOOSE(MONTH(Sales!$A208), "1", "1", "1", "2", "2", "2", "3", "3", "3", "4", "4", "4") & "_" & YEAR(Sales!$A208) -> Q1_2025 | D208: Karnataka | E208: Amazon | F208: MFN | G208: Jabala Mist | H208: Bundle | I208: JABALA MIST-3PCS | J208: 1 | K208: Organic | L208: 3 | M208: 259 | N208: 136
A209: 45717 | B209: 0.74375 | C209: ="Q" & CHOOSE(MONTH(Sales!$A209), "1", "1", "1", "2", "2", "2", "3", "3", "3", "4", "4", "4") & "_" & YEAR(Sales!$A209) -> Q1_2025 | D209: Telangana | E209: Amazon | F209: MFN | G209: Aroz Socks Size 1 | H209: Bundle | I209: AROZ SOCKS-(12-24M)-6PCS | J209: 1 | K209: Organic | L209: 2 | M209: 299 | N209: 148
A210: 45717 | B210: 0.81597222 | C210: ="Q" & CHOOSE(MONTH(Sales!$A210), "1", "1", "1", "2", "2", "2", "3", "3", "3", "4", "4", "4") & "_" & YEAR(Sales!$A210) -> Q1_2025 | D210: Karnataka | E210: Amazon | F210: MFN | G210: Jabala Wings | H210: Bundle | I210: JABALA WINGS-6PCS- 0-3M-S2 | J210: 1 | K210: Organic | L210: 6 | M210: 395 | N210: 246
A211: 45717 | B211: 0.84166667 | C211: ="Q" & CHOOSE(MONTH(Sales!$A211), "1", "1", "1", "2", "2", "2", "3", "3", "3", "4", "4", "4") & "_" & YEAR(Sales!$A211) -> Q1_2025 | D211: Tamil Nadu | E211: Amazon | F211: MFN | G211: Window Cradle Stand | H211: Single | I211: WND CRADLE STAND-1M-GRP | J211: 1 | K211: Organic | L211: 1 | M211: 734 | N211: 474
A212: 45717 | B212: 0.84930556 | C212: ="Q" & CHOOSE(MONTH(Sales!$A212), "1", "1", "1", "2", "2", "2", "3", "3", "3", "4", "4", "4") & "_" & YEAR(Sales!$A212) -> Q1_2025 | D212: Karnataka | E212: Amazon | F212: MFN | G212: Diaper Pad | H212: Bundle | I212: DIAPER PAD-5PCS | J212: 1 | K212: Organic | L212: 5 | M212: 509 | N212: 317
... A287: 45726 | B287: 0.23958333 | C287: ="Q" & CHOOSE(MONTH(Sales!$A287), "1", "1", "1", "2", "2", "2", "3", "3", "3", "4", "4", "4") & "_" & YEAR(Sales!$A287) -> Q1_2025 | D287: Karnataka | E287: Amazon | F287: MFN | G287: Hanger Plus | H287: Single | I287: HANGER PLUS-SILVER | J287: 1 | K287: Organic | L287: 1 | M287: 259 | N287: 115
A288: 45726 | B288: 0.3375 | C288: Q1_2025 | D288: Chhattisgarh | E288: Amazon | F288: MFN | G288: Diaper Pad | H288: Bundle | I288: DIAPER PAD-5PCS | J288: 1 | K288: Organic | L288: 5 | M288: 559 | N288: 361
A289: 45726 | B289: 0.37638889 | C289: Q1_2025 | D289: Kerala | E289: Amazon | F289: MFN | G289: Diaper Pad | H289: Bundle | I289: DIAPER PAD-3PCS | J289: 1 | K289: Organic | L289: 3 | M289: 359 | N289: 239
A290: 45726 | B290: 0.44930556 | C290: Q1_2025 | D290: Karnataka | E290: Amazon | F290: MFN | G290: Window Cradle Stand | H290: Single | I290: WND CRADLE STAND-1M-GRP | J290: 1 | K290: Organic | L290: 1 | M290: 861 | N290: 572
A291: 45726 | B291: 0.55694444 | C291: Q1_2025 | D291: Haryana | E291: Amazon | F291: MFN | G291: Zody Diaper | H291: Bundle | I291: ZODY DIAPER-5PCS | J291: 1 | K291: Organic | L291: 3 | M291: 1208.64 | N291: 930
A292: 45726 | B292: 0.55694444 | C292: Q1_2025 | D292: Haryana | E292: Amazon | F292: MFN | G292: Zody Diaper | H292: Single | I292: ZODY DIAPER-MC4 | J292: 1 | K292: Organic | L292: 1 | M292: 287.04 | N292: 159
A293: 45726 | B293: 0.55694444 | C293: Q1_2025 | D293: Haryana | E293: Amazon | F293: MFN | G293: Diaper Pad | H293: Bundle | I293: DIAPER PAD-3PCS | J293: 1 | K293: Organic | L293: 3 | M293: 344 | N293: 254
A294: 45726 | B294: 0.57083333 | C294: Q1_2025 | D294: Kerala | E294: Amazon | F294: MFN | G294: Diaper Pad | H294: Bundle | I294: DIAPER PAD-5PCS | J294: 1 | K294: Organic | L294: 5 | M294: 559 | N294: 361
A295: 45726 | B295: 0.5875 | C295: Q1_2025 | D295: Telangana | E295: Amazon | F295: MFN | G295: Diaper Pad | H295: Bundle | I295: DIAPER PAD-5PCS | J295: 1 | K295: Organic | L295: 5 | M295: 559 | N295: 361
A296: 45726 | B296: 0.84305556 | C296: Q1_2025 | D296: Karnataka | E296: Amazon | F296: MFN | G296: Cradle Spring with Hanger | H296: Single | I296: ANGEL_CRADLE_HANGER-GLD | J296: 1 | K296: Organic | L296: 1 | M296: 349 | N296: 190
A297: 45726 | B297: 0.86458333 | C297: Q1_2025 | D297: Andhra Pradesh | E297: Amazon | F297: MFN | G297: Cradle Spring with Hanger | H297: Single | I297: ANGEL_CRADLE_HANGER-GLD | J297: 1 | K297: Organic | L297: 1 | M297: 349 | N297: 190
A298: 45726 | B298: 0.86527778 | C298: Q1_2025 | D298: Delhi | E298: Amazon | F298: MFN | G298: Zody Diaper | H298: Single | I298: ZODY DIAPER-MC5 | J298: 1 | K298: Organic | L298: 1 | M298: 299 | N298: 176
A299: 45726 | B299: 0.86527778 | C299: Q1_2025 | D299: Delhi | E299: Amazon | F299: MFN | G299: Zody Diaper | H299: Single | I299: ZODY DIAPER-MC2 | J299: 1 | K299: Organic | L299: 1 | M299: 299 | N299: 176
... A302: 45726 | B302: 0.88263889 | C302: Q1_2025 | D302: Karnataka | E302: Amazon | F302: MFN | G302: Diaper Pad | H302: Bundle | I302: DIAPER PAD-2PCS | J302: 1 | K302: Organic | L302: 2 | M302: 279 | N302: 149
A303: 45724 | B303: 12 | C303: ="Q" & CHOOSE(MONTH(Sales!$A303), "1", "1", "1", "2", "2", "2", "3", "3", "3", "4", "4", "4") & "_" & YEAR(Sales!$A303) -> Q1_2025 | D303: N/A | E303: Meesho | F303: MFN | G303: Zody Diaper | H303: Bundle | I303: ZODY DIAPER-7PCS | J303: 1 | K303: Organic | L303: 7 | M303: 1405 | N303: 1405
A304: 45727 | B304: 0.42708333 | C304: ="Q" & CHOOSE(MONTH(Sales!$A304), "1", "1", "1", "2", "2", "2", "3", "3", "3", "4", "4", "4") & "_" & YEAR(Sales!$A304) -> Q1_2025 | D304: Maharashtra | E304: Amazon | F304: MFN | G304: Diaper Pad | H304: Bundle | I304: DIAPER PAD-3PCS | J304: 1 | K304: Organic | L304: 3 | M304: 358 | N304: 187
A305: 45727 | B305: 0.47777778 | C305: ="Q" & CHOOSE(MONTH(Sales!$A305), "1", "1", "1", "2", "2", "2", "3", "3", "3", "4", "4", "4") & "_" & YEAR(Sales!$A305) -> Q1_2025 | D305: Tamil Nadu | E305: Amazon | F305: MFN | G305: Cradle Spring with Hanger | H305: Single | I305: ANGEL_CRADLE_HANGER-GLD | J305: 1 | K305: Organic | L305: 1 | M305: 365 | N305: 227
A306: 45727 | B306: 0.56180556 | C306: ="Q" & CHOOSE(MONTH(Sales!$A306), "1", "1", "1", "2", "2", "2", "3", "3", "3", "4", "4", "4") & "_" & YEAR(Sales!$A306) -> Q1_2025 | D306: Karnataka | E306: Amazon | F306: MFN | G306: Window Cradle Stand | H306: Single | I306: WND CRADLE STAND-1M-GRP | J306: 1 | K306: Organic | L306: 1 | M306: 889 | N306: 541
A307: 45727 | B307: 0.59305556 | C307: ="Q" & CHOOSE(MONTH(Sales!$A307), "1", "1", "1", "2", "2", "2", "3", "3", "3", "4", "4", "4") & "_" & YEAR(Sales!$A307) -> Q1_2025 | D307: Telangana | E307: Amazon | F307: MFN | G307: Jabala Wings | H307: Bundle | I307: JABALA WINGS-6PCS- 3-6M-S1 | J307: 1 | K307: Organic | L307: 6 | M307: 449 | N307: 300
A308: 45727 | B308: 0.69513889 | C308: ="Q" & CHOOSE(MONTH(Sales!$A308), "1", "1", "1", "2", "2", "2", "3", "3", "3", "4", "4", "4") & "_" & YEAR(Sales!$A308) -> Q1_2025 | D308: Jammu and Kashmir | E308: Amazon | F308: MFN | G308: Feeding Bed | H308: Single | I308: FEEDING BED-GRY&WHT | J308: 1 | K308: Organic | L308: 1 | M308: 789 | N308: 533
A309: 45727 | B309: 0.80833333 | C309: ="Q" & CHOOSE(MONTH(Sales!$A309), "1", "1", "1", "2", "2", "2", "3", "3", "3", "4", "4", "4") & "_" & YEAR(Sales!$A309) -> Q1_2025 | D309: Telangana | E309: Amazon | F309: MFN | G309: Cradle Spring with Hanger | H309: Single | I309: ANGEL_CRADLE_HANGER-GLD | J309: 1 | K309: Organic | L309: 1 | M309: 364 | N309: 192
A310: 45728 | B310: 0.15763889 | C310: ="Q" & CHOOSE(MONTH(Sales!$A310), "1", "1", "1", "2", "2", "2", "3", "3", "3", "4", "4", "4") & "_" & YEAR(Sales!$A310) -> Q1_2025 | D310: Maharashtra | E310: Amazon | F310: MFN | G310: Diaper Pad | H310: Bundle | I310: DIAPER PAD-5PCS | J310: 1 | K310: Organic | L310: 5 | M310: 555 | N310: 357
A311: 45728 | B311: 0.47777778 | C311: ="Q" & CHOOSE(MONTH(Sales!$A311), "1", "1", "1", "2", "2", "2", "3", "3", "3", "4", "4", "4") & "_" & YEAR(Sales!$A311) -> Q1_2025 | D311: Karnataka | E311: Amazon | F311: MFN | G311: Diaper Pad | H311: Bundle | I311: DIAPER PAD-3PCS | J311: 1 | K311: Organic | L311: 3 | M311: 359 | N311: 228
A312: 45728 | B312: 0.80555556 | C312: ="Q" & CHOOSE(MONTH(Sales!$A312), "1", "1", "1", "2", "2", "2", "3", "3", "3", "4", "4", "4") & "_" & YEAR(Sales!$A312) -> Q1_2025 | D312: Tamil Nadu | E312: Amazon | F312: MFN | G312: Hanger Plus | H312: Single | I312: HANGER PLUS-SILVER | J312: 1 | K312: Organic | L312: 1 | M312: 243 | N312: 142
A313: 45728 | B313: 0.83125 | C313: ="Q" & CHOOSE(MONTH(Sales!$A313), "1", "1", "1", "2", "2", "2", "3", "3", "3", "4", "4", "4") & "_" & YEAR(Sales!$A313) -> Q1_2025 | D313: Tamil Nadu | E313: Amazon | F313: MFN | G313: Window Cradle Stand | H313: Single | I313: WND CRADLE STAND-1M-GRP | J313: 1 | K313: Organic | L313: 1 | M313: 889 | N313: 541
A314: 45728 | B314: 0.84513889 | C314: ="Q" & CHOOSE(MONTH(Sales!$A314), "1", "1", "1", "2", "2", "2", "3", "3", "3", "4", "4", "4") & "_" & YEAR(Sales!$A314) -> Q1_2025 | D314: Kerala | E314: Amazon | F314: MFN | G314: Diaper Pad | H314: Bundle | I314: DIAPER PAD-2PCS | J314: 1 | K314: Organic | L314: 2 | M314: 268 | N314: 148
... A687: 45776 | B687: 0.97708333 | C687: ="Q" & CHOOSE(MONTH(Sales!$A687), "1", "1", "1", "2", "2", "2", "3", "3", "3", "4", "4", "4") & "_" & YEAR(Sales!$A687) -> Q2_2025 | D687: Maharashtra | E687: Amazon | F687: MFN | G687: Diaper Pad | H687: Bundle | I687: DIAPER PAD-9PCS | J687: 1 | K687: Organic | L687: 9 | M687: 789 | N687: 566

Sheet Feb-25
A1: Date | B1: Order qty | C1: Order Value | D1: O_Total | E1: setlement | F1: S_Total | G1: Advertisment spend | H1: Returns_Amt | I1: Returns_Vol
A2: =Sales!A28 -> 45690 | B2: =SUMIF(Sales!A:A, A2, Sales!K:K) -> 0 | C2: =SUMIF(Sales!A:A, A2, Sales!N:N) -> 340 | D2: =SUM($C$2) -> 340 | E2: =179+179+211.08+155.76 -> 724.84 | F2: =SUM($C$2) -> 340 | G2: 32
A3: =Sales!A32 -> 45691 | B3: =SUMIF(Sales!A:A, A3, Sales!K:K) -> 0 | C3: =SUMIF(Sales!A:A, A3, Sales!N:N) -> 0 | D3: =SUM($C$2+$C$3) -> 340 | E3: =SUM(881+173+371+136+167+570+416+211+211+265) -> 3401 | F3: =SUM(E$2+E$3) -> 4125.84 | G3: 46 | H3: 0
A4: =Sales!A42 -> 45692 | B4: =SUMIF(Sales!A:A, A4, Sales!K:K) -> 0 | C4: =SUMIF(Sales!A:A, A4, Sales!N:N) -> 340 | D4: =SUM($C$2+$C$3+$C$4) -> 680 | E4: =SUM(179+179+174) -> 532 | F4: =SUM($E$3+$E$4+$E$2) -> 4657.84 | G4: 112 | H4: 0
A5: =Sales!A45 -> 45693 | B5: =SUMIF(Sales!A:A, A5, Sales!K:K) -> 0 | C5: =SUMIF(Sales!A:A, A5, Sales!N:N) -> 0 | D5: =SUM($C$2+$C$3+$C$4+$C$5) -> 680 | E5: =SUM(369+886) -> 1255 | F5: =SUM($E$4+$E$5+$E$3+$E$2) -> 5912.84 | G5: 150 | H5: 0
A6: =Sales!A48 -> 45694 | B6: =SUMIF(Sales!A:A, A6, Sales!K:K) -> 0 | C6: =SUMIF(Sales!A:A, A6, Sales!N:N) -> 0 | D6: =SUM($C$2+$C$3+$C$4+$C$5+$C$6) -> 680 | E6: =SUM(416+173+570+614) -> 1773 | F6: =SUM($E$2+$E$5+$E$6+$E$4+$E$3) -> 7685.84 | G6: 170 | H6: 0
A7: =Sales!A54 -> 45695 | B7: =SUMIF(Sales!A:A, A7, Sales!K:K) -> 0 | C7: =SUMIF(Sales!A:A, A7, Sales!N:N) -> 0 | D7: =SUM($C$2+$C$3+$C$4+$C$5+$C$6+$C$7) -> 680 | E7: =SUM(145+173+167+283+283+87) -> 1138 | F7: =SUM($E$2+$E$5+$E$6+$E$4+$E$3+E7) -> 8823.84 | G7: 59 | H7: 0
A8: =Sales!A60 -> 45696 | B8: =SUMIF(Sales!A:A, A8, Sales!K:K) -> 0 | C8: =SUMIF(Sales!A:A, A8, Sales!N:N) -> 0 | D8: =SUM($C$2+$C$3+$C$4+$C$5+$C$6+$C$7+$C$8) -> 680 | E8: =SUM(283+378) -> 661 | F8: =SUM($E$2+$E$5+$E$6+$E$4+$E$3+$E$8+$E$7) -> 9484.84 | G8: 65 | H8: 349
A9: =Sales!A62 -> 45697 | B9: =SUMIF(Sales!A:A, A9, Sales!K:K) -> 0 | C9: =SUMIF(Sales!A:A, A9, Sales!N:N) -> 0 | D9: =SUM($C$2+$C$3+$C$4+$C$5+$C$6+$C$7+$C$8+$C$9) -> 680 | E9: =SUM(500+167+173+881) -> 1721 | F9: =SUM($E$2+$E$5+$E$6+$E$4+$E$3+$E$8+$E$7+$E$9) -> 11205.84 | G9: 53 | H9: 0
A10: =Sales!A67 -> 45698 | B10: =SUMIF(Sales!A:A, A10, Sales!K:K) -> 0 | C10: =SUMIF(Sales!A:A, A10, Sales!N:N) -> 0 | D10: =SUM($C$2+$C$3+$C$4+$C$5+$C$6+$C$7+$C$8+$C$9+$C$10) -> 680 | E10: =SUM(233+87) -> 320 | F10: =SUM($E$2+$E$5+$E$6+$E$4+$E$3+$E$8+$E$7+$E$9+$E$10) -> 11525.84 | G10: 25 | H10: 299
A11: =Sales!A69 -> 45699 | B11: =SUMIF(Sales!A:A, A11, Sales!K:K) -> 0 | C11: =SUMIF(Sales!A:A, A11, Sales!N:N) -> 0 | D11: =SUM($C$2+$C$3+$C$4+$C$5+$C$6+$C$7+$C$8+$C$9+$C$10+$C$11) -> 680 | E11: =SUM(173+162+148+87+173) -> 743 | F11: =SUM($E$2+$E$5+$E$6+$E$4+$E$3+$E$8+$E$7+$E$9+$E$10+$E$11) -> 12268.84 | G11: 106 | H11: 0
A12: =Sales!A74 -> 45700 | B12: =SUMIF(Sales!A:A, A12, Sales!K:K) -> 0 | C12: =SUMIF(Sales!A:A, A12, Sales!N:N) -> 87.34 | D12: =SUM($C$2+$C$3+$C$4+$C$5+$C$6+$C$7+$C$8+$C$9+$C$10+$C$11+$C$12) -> 767.34 | E12: =87+163+163 -> 413 | F12: =SUM($E$2+$E$5+$E$6+$E$4+$E$3+$E$8+$E$7+$E$9+$E$10+$E$11+$E$12) -> 12681.84 | G12: 67
A13: 45701 | B13: 4 | C13: 1567 | D13: =SUM($C$2+$C$3+$C$4+$C$5+$C$6+$C$7+$C$8+$C$9+$C$10+$C$11+$C$12+$C$13) -> 2334.34 | E13: 987 | F13: =SUM($E$2+$E$5+$E$6+$E$4+$E$3+$E$8+$E$7+$E$9+$E$10+$E$11+$E$12+$E$13) -> 13668.84 | G13: 127 | H13: 637
A14: 45702 | B14: 4 | C14: 1286 | D14: =SUM($C$2+$C$3+$C$4+$C$5+$C$6+$C$7+$C$8+$C$9+$C$10+$C$11+$C$12+$C$13+$C$14) -> 3620.34 | E14: 784 | F14: =SUM($E$2+$E$5+$E$6+$E$4+$E$3+$E$8+$E$7+$E$9+$E$10+$E$11+$E$12+$E$13+$E$14) -> 14452.84 | G14: 117 | H14: 0
A15: 45703 | B15: 12 | C15: 4956.66 | D15: =SUM($C$2+$C$3+$C$4+$C$5+$C$6+$C$7+$C$8+$C$9+$C$10+$C$11+$C$12+$C$13+$C$14+$C$15) -> 8577 | E15: 3267.86 | F15: =SUM($E$2+$E$5+$E$6+$E$4+$E$3+$E$8+$E$7+$E$9+$E$10+$E$11+$E$12+$E$13+$E$14+$E$15) -> 17720.7 | G15: 100 | H15: 0
A16: 45704 | B16: 7 | C16: 2594 | D16: =SUM($C$2+$C$3+$C$4+$C$5+$C$6+$C$7+$C$8+$C$9+$C$10+$C$11+$C$12+$C$13+$C$14+$C$15+$C$16) -> 11171 | E16: 1720 | F16: =SUM($E$2+$E$5+$E$6+$E$4+$E$3+$E$8+$E$7+$E$9+$E$10+$E$11+$E$12+$E$13+$E$14+$E$15+$E$16) -> 19440.7 | G16: 262 | H16: 0
A17: 45705 | B17: 10 | C17: 3406 | D17: =SUM($C$2+$C$3+$C$4+$C$5+$C$6+$C$7+$C$8+$C$9+$C$10+$C$11+$C$12+$C$13+$C$14+$C$15+$C$16+$C$17) -> 14577 | E17: 2138 | F17: =SUM($E$2+$E$5+$E$6+$E$4+$E$3+$E$8+$E$7+$E$9+$E$10+$E$11+$E$12+$E$13+$E$14+$E$15+$E$16+$E$17) -> 21578.7 | G17: 149 | H17: 635
A18: 45706 | B18: 5 | C18: 1755 | D18: =SUM($C$2+$C$3+$C$4+$C$5+$C$6+$C$7+$C$8+$C$9+$C$10+$C$11+$C$12+$C$13+$C$14+$C$15+$C$16+$C$17+$C$18) -> 16332 | E18: 1097 | F18: =SUM($E$2+$E$5+$E$6+$E$4+$E$3+$E$8+$E$7+$E$9+$E$10+$E$11+$E$12+$E$13+$E$14+$E$15+$E$16+$E$17+$E$18) -> 22675.7 | G18: 118 | H18: 0
A19: 45707 | B19: 6 | C19: 2914 | D19: =SUM($C$2+$C$3+$C$4+$C$5+$C$6+$C$7+$C$8+$C$9+$C$10+$C$11+$C$12+$C$13+$C$14+$C$15+$C$16+$C$17+$C$18+$C$19) -> 19246 | E19: 1954 | F19: =SUM($E$2+$E$5+$E$6+$E$4+$E$3+$E$8+$E$7+$E$9+$E$10+$E$11+$E$12+$E$13+$E$14+$E$15+$E$16+$E$17+$E$18+$E$19) -> 24629.7 | G19: 210 | H19: 179
A20: 45708 | B20: 9 | C20: 3593 | D20: =SUM($C$2+$C$3+$C$4+$C$5+$C$6+$C$7+$C$8+$C$9+$C$10+$C$11+$C$12+$C$13+$C$14+$C$15+$C$16+$C$17+$C$18+$C$19+C20) -> 22839 | E20: 2409 | F20: =SUM($E$2+$E$5+$E$6+$E$4+$E$3+$E$8+$E$7+$E$9+$E$10+$E$11+$E$12+$E$13+$E$14+$E$15+$E$16+$E$17+$E$18+$E$20+$E$19) -> 27038.7 | G20: 180 | H20: 284
A21: 45709 | B21: 4 | C21: 1374 | D21: =SUM($C$2+$C$3+$C$4+$C$5+$C$6+$C$7+$C$8+$C$9+$C$10+$C$11+$C$12+$C$13+$C$14+$C$15+$C$16+$C$17+$C$18+$C$19+$C$21+$C$20) -> 24213 | E21: 861 | F21: =SUM($E$2+$E$5+$E$6+$E$4+$E$3+$E$8+$E$7+$E$9+$E$10+$E$11+$E$12+$E$13+$E$14+$E$15+$E$16+$E$17+$E$18+$E$21+$E$19+$E$20) -> 27899.7 | G21: 93 | H21: 0
A22: 45710 | B22: 10 | C22: 4487 | D22: =SUM($C$2+$C$3+$C$4+$C$5+$C$6+$C$7+$C$8+$C$9+$C$10+$C$11+$C$12+$C$13+$C$14+$C$15+$C$16+$C$17+$C$18+$C$19+$C$21+$C$20+$C$22) -> 28700 | E22: 3209 | F22: =SUM($E$2+$E$5+$E$6+$E$4+$E$3+$E$8+$E$7+$E$9+$E$10+$E$11+$E$12+$E$13+$E$14+$E$15+$E$16+$E$17+$E$18+$E$21+$E$19+$E$20+$E$22) -> 31108.7 | G22: 193 | H22: 399
A23: 45711 | B23: 5 | C23: 2735 | D23: =SUM($C$2+$C$3+$C$4+$C$5+$C$6+$C$7+$C$8+$C$9+$C$10+$C$11+$C$12+$C$13+$C$14+$C$15+$C$16+$C$17+$C$18+$C$19+$C$21+$C$20+$C$22+$C$23) -> 31435 | E23: 1837 | F23: =SUM($E$2+$E$5+$E$6+$E$4+$E$3+$E$8+$E$7+$E$9+$E$10+$E$11+$E$12+$E$13+$E$14+$E$15+$E$16+$E$17+$E$18+$E$21+$E$19+$E$20+$E$22+$E$23) -> 32945.7 | G23: 216 | H23: 0
A24: 45712 | B24: 7 | C24: 2718 | D24: =SUM($C$2+$C$3+$C$4+$C$5+$C$6+$C$7+$C$8+$C$9+$C$10+$C$11+$C$12+$C$13+$C$14+$C$15+$C$16+$C$17+$C$18+$C$19+$C$21+$C$20+$C$22+$C$23+$C$24) -> 34153 | E24: 1685 | F24: =SUM($E$2+$E$5+$E$6+$E$4+$E$3+$E$8+$E$7+$E$9+$E$10+$E$11+$E$12+$E$13+$E$14+$E$15+$E$16+$E$17+$E$18+$E$21+$E$19+$E$20+$E$22+$E$23+$E$24) -> 34630.7 | G24: 309 | H24: 419
A25: 45713 | B25: 17 | C25: 6765 | D25: =SUM($C$2+$C$3+$C$4+$C$5+$C$6+$C$7+$C$8+$C$9+$C$10+$C$11+$C$12+$C$13+$C$14+$C$15+$C$16+$C$17+$C$18+$C$19+$C$21+$C$20+$C$22+$C$23+$C$24+$C$25) -> 40918 | E25: 4596 | F25: =SUM($E$2+$E$5+$E$6+$E$4+$E$3+$E$8+$E$7+$E$9+$E$10+$E$11+$E$12+$E$13+$E$14+$E$15+$E$16+$E$17+$E$18+$E$21+$E$19+$E$20+$E$22+$E$23+$E$24+$E$25) -> 39226.7 | G25: 143 | H25: =SUMIF(Returns!B:B, A25, Returns!P:P) -> 0
A26: 45714 | B26: 9 | C26: 4263 | D26: =SUM($C$2+$C$3+$C$4+$C$5+$C$6+$C$7+$C$8+$C$9+$C$10+$C$11+$C$12+$C$13+$C$14+$C$15+$C$16+$C$17+$C$18+$C$19+$C$21+$C$20+$C$22+$C$23+$C$24+$C$25+$C$26) -> 45181 | E26: 2864 | F26: =SUM($E$2+$E$5+$E$6+$E$4+$E$3+$E$8+$E$7+$E$9+$E$10+$E$11+$E$12+$E$13+$E$14+$E$15+$E$16+$E$17+$E$18+$E$21+$E$19+$E$20+$E$22+$E$23+$E$24+$E$25+$E$26) -> 42090.7 | G26: 71 | H26: =SUMIF(Returns!B:B, A26, Returns!P:P) -> 0
A27: 45715 | B27: 11 | C27: 4319 | D27: =SUM($C$2+$C$3+$C$4+$C$5+$C$6+$C$7+$C$8+$C$9+$C$10+$C$11+$C$12+$C$13+$C$14+$C$15+$C$16+$C$17+$C$18+$C$19+$C$21+$C$20+$C$22+$C$23+$C$24+$C$25+$C$26+$C$27) -> 49500 | E27: 3010.95 | F27: =SUM($E$2+$E$5+$E$6+$E$4+$E$3+$E$8+$E$7+$E$9+$E$10+$E$11+$E$12+$E$13+$E$14+$E$15+$E$16+$E$17+$E$18+$E$21+$E$19+$E$20+$E$22+$E$23+$E$24+$E$25+$E$26+$E$27) -> 45101.65 | G27: 284 | H27: =SUMIF(Returns!B:B, A27, Returns!P:P) -> 314
A28: 45716 | B28: 7 | C28: 2643 | D28: =SUM($C$2+$C$3+$C$4+$C$5+$C$6+$C$7+$C$8+$C$9+$C$10+$C$11+$C$12+$C$13+$C$14+$C$15+$C$16+$C$17+$C$18+$C$19+$C$21+$C$20+$C$22+$C$23+$C$24+$C$25+$C$26+$C$27+$C$28) -> 52143 | E28: 1732 | F28: =SUM($E$2+$E$5+$E$6+$E$4+$E$3+$E$8+$E$7+$E$9+$E$10+$E$11+$E$12+$E$13+$E$14+$E$15+$E$16+$E$17+$E$18+$E$21+$E$19+$E$20+$E$22+$E$23+$E$24+$E$25+$E$26+$E$27+$E$28) -> 46833.65 | G28: 320 | H28: =SUMIF(Returns!B:B, A28, Returns!P:P) -> 0
A30: Date | B30: Order qty | C30: Order Value | D30: O_Total | E30: setlement | F30: S_Total | G30: Advertisment spend | H30: Returns | I30: Returns_Vol
A31: =Sales!A201 -> 45717 | B31: =SUMIF(Sales!A:A, A31, Sales!J:J) -> 15 | C31: =SUMIF(Sales!A:A, A31,Sales!M:M) -> 7972 | D31: =SUM(C31) -> 7972 | E31: =SUMIF(Sales!A:A, A31, Sales!N:N) -> 4996 | F31: =SUM(E31) -> 4996 | G31: 433 | H31: =SUMIF(Returns!B:B, A31, Returns!P:P) -> 0 | I31: =SUMIF(Returns!B:B, A31, Returns!L:L) -> 0
A32: =Sales!A218 -> 45718 | B32: =SUMIF(Sales!A:A, A32, Sales!J:J) -> 10 | C32: =SUMIF(Sales!A:A, A32,Sales!M:M) -> 4260 | D32: =SUM($C$32+$C$31) -> 12232 | E32: =SUMIF(Sales!A:A, A32, Sales!N:N) -> 2709 | F32: =SUM($E$32+$E$31) -> 7705 | G32: 242 | H32: =SUMIF(Returns!B:B, A32, Returns!P:P) -> 0 | I32: =SUMIF(Returns!B:B, A32, Returns!L:L) -> 0
A33: =Sales!A226 -> 45719 | B33: =SUMIF(Sales!A:A, A33, Sales!J:J) -> 9 | C33: =SUMIF(Sales!A:A, A33,Sales!M:M) -> 3383 | D33: =SUM($C$32+$C$31+$C$33) -> 15615 | E33: =SUMIF(Sales!A:A, A33, Sales!N:N) -> 2103 | F33: =SUM($E$32+$E$31+$E$33) -> 9808 | G33: 94 | H33: =SUMIF(Returns!B:B, A33, Returns!P:P) -> 738 | I33: =SUMIF(Returns!B:B, A33, Returns!L:L) -> 3
A34: =Sales!A239 -> 45720 | B34: =SUMIF(Sales!A:A, A34, Sales!J:J) -> 6 | C34: =SUMIF(Sales!A:A, A34,Sales!M:M) -> 2005 | D34: =SUM($C$32+$C$31+$C$33+$C$34) -> 17620 | E34: =SUMIF(Sales!A:A, A34, Sales!N:N) -> 1182 | F34: =SUM($E$32+$E$31+$E$33+$E$34) -> 10990 | G34: 54 | H34: =SUMIF(Returns!B:B, A34, Returns!P:P) -> 0 | I34: =SUMIF(Returns!B:B, A34, Returns!L:L) -> 0
A35: =Sales!A248 -> 45721 | B35: =SUMIF(Sales!A:A, A35, Sales!J:J) -> 12 | C35: =SUMIF(Sales!A:A, A35,Sales!M:M) -> 4745 | D35: =SUM($C$32+$C$31+$C$33+$C$34+$C$35) -> 22365 | E35: =SUMIF(Sales!A:A, A35, Sales!N:N) -> 2935 | F35: =SUM($E$32+$E$31+$E$33+$E$34+$E$35) -> 13925 | G35: 219 | H35: =SUMIF(Returns!B:B, A35, Returns!P:P) -> 0 | I35: =SUMIF(Returns!B:B, A35, Returns!L:L) -> 0
A36: =Sales!A263 -> 45722 | B36: =SUMIF(Sales!A:A, A36, Sales!J:J) -> 12 | C36: =SUMIF(Sales!A:A, A36,Sales!M:M) -> 6122 | D36: =SUM($C$32+$C$31+$C$33+$C$34+$C$35+$C$36) -> 28487 | E36: =SUMIF(Sales!A:A, A36, Sales!N:N) -> 4034 | F36: =SUM($E$32+$E$31+$E$33+$E$34+$E$35+$E$36) -> 17959 | G36: 165 | H36: =SUMIF(Returns!B:B, A36, Returns!P:P) -> 0 | I36: =SUMIF(Returns!B:B, A36, Returns!L:L) -> 0
A37: =Sales!A266 -> 45723 | B37: =SUMIF(Sales!A:A, A37, Sales!J:J) -> 5 | C37: =SUMIF(Sales!A:A, A37,Sales!M:M) -> 1933 | D37: =SUM($C$32+$C$31+$C$33+$C$34+$C$35+$C$36+C37) -> 30420 | E37: =SUMIF(Sales!A:A, A37, Sales!N:N) -> 1219 | F37: =SUM($E$32+$E$31+$E$33+$E$34+$E$35+$E$36+$E$37) -> 19178 | G37: 144 | H37: =SUMIF(Returns!B:B, A37, Returns!P:P) -> 778 | I37: =SUMIF(Returns!B:B, A37, Returns!L:L) -> 2
A38: =Sales!A274 -> 45724 | B38: =SUMIF(Sales!A:A, A38, Sales!J:J) -> 8 | C38: =SUMIF(Sales!A:A, A38,Sales!M:M) -> 4110 | D38: =SUM($C$32+$C$31+$C$33+$C$34+$C$35+$C$36+$C$38+$C$37) -> 34530 | E38: =SUMIF(Sales!A:A, A38, Sales!N:N) -> 3109 | F38: =SUM($E$32+$E$31+$E$33+$E$34+$E$35+$E$36+$E$37+$E$38) -> 22287 | G38: 310 | H38: =SUMIF(Returns!B:B, A38, Returns!P:P) -> 329 | I38: =SUMIF(Returns!B:B, A38, Returns!L:L) -> 1
A39: =Sales!A286 -> 45725 | B39: =SUMIF(Sales!A:A, A39, Sales!J:J) -> 12 | C39: =SUMIF(Sales!A:A, A39,Sales!M:M) -> 5469.03 | D39: =SUM($C$32+$C$31+$C$33+$C$34+$C$35+$C$36+$C$39+$C$37+$C$38) -> 39999.03 | E39: =SUMIF(Sales!A:A, A39, Sales!N:N) -> 3579 | F39: =SUM($E$32+$E$31+$E$33+$E$34+$E$35+$E$36+$E$37+$E$38+$E$39) -> 25866 | G39: 398 | H39: =SUMIF(Returns!B:B, A39, Returns!P:P) -> 0 | I39: =SUMIF(Returns!B:B, A39, Returns!L:L) -> 0
A40: 45726 | B40: =SUMIF(Sales!A:A, A40, Sales!J:J) -> 16 | C40: =SUMIF(Sales!A:A, A40,Sales!M:M) -> 7168.68 | D40: =SUM($C$32+$C$31+$C$33+$C$34+$C$35+$C$36+$C$39+$C$37+$C$38+$C$40) -> 47167.71 | E40: =SUMIF(Sales!A:A, A40, Sales!N:N) -> 4585 | F40: =SUM($E$32+$E$31+$E$33+$E$34+$E$35+$E$36+$E$37+$E$38+$E$39+$E$40) -> 30451 | G40: 115 | H40: =SUMIF(Returns!B:B, A40, Returns!P:P) -> 0 | I40: =SUMIF(Returns!B:B, A40, Returns!L:L) -> 0
A41: 45727 | B41: =SUMIF(Sales!A:A, A41, Sales!J:J) -> 6 | C41: =SUMIF(Sales!A:A, A41,Sales!M:M) -> 3214 | D41: =SUM($C$32+$C$31+$C$33+$C$34+$C$35+$C$36+$C$39+$C$37+$C$38+$C$40+$C$41) -> 50381.71 | E41: =SUMIF(Sales!A:A, A41, Sales!N:N) -> 1980 | F41: =SUM($E$32+$E$31+$E$33+$E$34+$E$35+$E$36+$E$37+$E$38+$E$39+$E$40+$E$41) -> 32431 | G41: 90 | H41: =SUMIF(Returns!B:B, A41, Returns!P:P) -> 0 | I41: =SUMIF(Returns!B:B, A41, Returns!L:L) -> 0
A42: 45728 | B42: =SUMIF(Sales!A:A, A42, Sales!J:J) -> 14 | C42: =SUMIF(Sales!A:A, A42,Sales!M:M) -> 6882 | D42: =SUM($C$32+$C$31+$C$33+$C$34+$C$35+$C$36+$C$39+$C$37+$C$38+$C$40+$C$41+$C$42) -> 57263.71 | E42: =SUMIF(Sales!A:A, A42, Sales!N:N) -> 4317 | F42: =SUM($E$32+$E$31+$E$33+$E$34+$E$35+$E$36+$E$37+$E$38+$E$39+$E$40+$E$41+$E$42) -> 36748 | G42: 54 | H42: =SUMIF(Returns!B:B, A42, Returns!P:P) -> 0 | I42: =SUMIF(Returns!B:B, A42, Returns!L:L) -> 0
A43: 45729 | B43: =SUMIF(Sales!A:A, A43, Sales!J:J) -> 12 | C43: =SUMIF(Sales!A:A, A43,Sales!M:M) -> 4849 | D43: =SUM($C$32+$C$31+$C$33+$C$34+$C$35+$C$36+$C$39+$C$37+$C$38+$C$40+$C$41+$C$42+$C$43) -> 62112.71 | E43: =SUMIF(Sales!A:A, A43, Sales!N:N) -> 2935 | F43: =SUM($E$32+$E$31+$E$33+$E$34+$E$35+$E$36+$E$37+$E$38+$E$39+$E$40+$E$41+$E$42+$E$43) -> 39683 | G43: 98 | H43: =SUMIF(Returns!B:B, A43, Returns!P:P) -> 0 | I43: =SUMIF(Returns!B:B, A43, Returns!L:L) -> 0
A44: 45730 | B44: =SUMIF(Sales!A:A, A44, Sales!J:J) -> 16 | C44: =SUMIF(Sales!A:A, A44,Sales!M:M) -> 6576 | D44: =SUM($C$32+$C$31+$C$33+$C$34+$C$35+$C$36+$C$39+$C$37+$C$38+$C$40+$C$41+$C$42+$C$43+$C$44) -> 68688.71 | E44: =SUMIF(Sales!A:A, A44, Sales!N:N) -> 4252 | F44: =SUM($E$32+$E$31+$E$33+$E$34+$E$35+$E$36+$E$37+$E$38+$E$39+$E$40+$E$41+$E$42+$E$43+$E$44) -> 43935 | G44: 74 | H44: =SUMIF(Returns!B:B, A44, Returns!P:P) -> 0 | I44: =SUMIF(Returns!B:B, A44, Returns!L:L) -> 0
A45: 45731 | B45: =SUMIF(Sales!A:A, A45, Sales!J:J) -> 11 | C45: =SUMIF(Sales!A:A, A45,Sales!M:M) -> 4803 | D45: =SUM($C$32+$C$31+$C$33+$C$34+$C$35+$C$36+$C$39+$C$37+$C$38+$C$40+$C$41+$C$42+$C$43+$C$44+$C$45) -> 73491.71 | E45: =SUMIF(Sales!A:A, A45, Sales!N:N) -> 3023 | F45: =SUM($E$32+$E$31+$E$33+$E$34+$E$35+$E$36+$E$37+$E$38+$E$39+$E$40+$E$41+$E$42+$E$43+$E$44+$E$45) -> 46958 | G45: 143 | H45: =SUMIF(Returns!B:B, A45, Returns!P:P) -> 968.6 | I45: =SUMIF(Returns!B:B, A45, Returns!L:L) -> 2
A46: 45732 | B46: =SUMIF(Sales!A:A, A46, Sales!J:J) -> 9 | C46: =SUMIF(Sales!A:A, A46,Sales!M:M) -> 4488 | D46: =SUM($C$32+$C$31+$C$33+$C$34+$C$35+$C$36+$C$39+$C$37+$C$38+$C$40+$C$41+$C$42+$C$43+$C$44+$C$45+$C$46) -> 77979.71 | E46: =SUMIF(Sales!A:A, A46, Sales!N:N) -> 2876 | F46: =SUM($E$32+$E$31+$E$33+$E$34+$E$35+$E$36+$E$37+$E$38+$E$39+$E$40+$E$41+$E$42+$E$43+$E$44+$E$45+$E$46) -> 49834 | G46: 187 | H46: =SUMIF(Returns!B:B, A46, Returns!P:P) -> 0 | I46: =SUMIF(Returns!B:B, A46, Returns!L:L) -> 0
A47: 45733 | B47: =SUMIF(Sales!A:A, A47, Sales!J:J) -> 8 | C47: =SUMIF(Sales!A:A, A47,Sales!M:M) -> 5007 | D47: =SUM($C$32+$C$31+$C$33+$C$34+$C$35+$C$36+$C$39+$C$37+$C$38+$C$40+$C$41+$C$42+$C$43+$C$44+$C$45+$C$46+$C$47) -> 82986.71 | E47: =SUMIF(Sales!A:A, A47, Sales!N:N) -> 3270 | F47: =SUM($E$32+$E$31+$E$33+$E$34+$E$35+$E$36+$E$37+$E$38+$E$39+$E$40+$E$41+$E$42+$E$43+$E$44+$E$45+$E$46+$E$47) -> 53104 | G47: 152 | H47: =SUMIF(Returns!B:B, A47, Returns!P:P) -> 0 | I47: =SUMIF(Returns!B:B, A47, Returns!L:L) -> 0
A48: 45734 | B48: =SUMIF(Sales!A:A, A48, Sales!J:J) -> 9 | C48: =SUMIF(Sales!A:A, A48,Sales!M:M) -> 5880 | D48: =SUM($C$32+$C$31+$C$33+$C$34+$C$35+$C$36+$C$39+$C$37+$C$38+$C$40+$C$41+$C$42+$C$43+$C$44+$C$45+$C$46+$C$47+$C$48) -> 88866.71 | E48: =SUMIF(Sales!A:A, A48, Sales!N:N) -> 3922 | F48: =SUM($E$32+$E$31+$E$33+$E$34+$E$35+$E$36+$E$37+$E$38+$E$39+$E$40+$E$41+$E$42+$E$43+$E$44+$E$45+$E$46+$E$47+$E$48) -> 57026 | G48: 89 | H48: =SUMIF(Returns!B:B, A48, Returns!P:P) -> 798 | I48: =SUMIF(Returns!B:B, A48, Returns!L:L) -> 2
A49: 45735 | B49: =SUMIF(Sales!A:A, A49, Sales!J:J) -> 6 | C49: =SUMIF(Sales!A:A, A49,Sales!M:M) -> 2638 | D49: =SUM($C$32+$C$31+$C$33+$C$34+$C$35+$C$36+$C$39+$C$37+$C$38+$C$40+$C$41+$C$42+$C$43+$C$44+$C$45+$C$46+$C$47+$C$48+$C$49) -> 91504.71 | E49: =SUMIF(Sales!A:A, A49, Sales!N:N) -> 1577 | F49: =SUM($E$32+$E$31+$E$33+$E$34+$E$35+$E$36+$E$37+$E$38+$E$39+$E$40+$E$41+$E$42+$E$43+$E$44+$E$45+$E$46+$E$47+$E$48+$E$49) -> 58603 | G49: 53 | H49: =SUMIF(Returns!B:B, A49, Returns!P:P) -> 0 | I49: =SUMIF(Returns!B:B, A49, Returns!L:L) -> 0
A50: 45736 | B50: =SUMIF(Sales!A:A, A50, Sales!J:J) -> 11 | C50: =SUMIF(Sales!A:A, A50,Sales!M:M) -> 7477 | D50: =SUM($C$32+$C$31+$C$33+$C$34+$C$35+$C$36+$C$39+$C$37+$C$38+$C$40+$C$41+$C$42+$C$43+$C$44+$C$45+$C$46+$C$47+$C$48+$C$49+$C$50) -> 98981.71 | E50: =SUMIF(Sales!A:A, A50, Sales!N:N) -> 5132 | F50: =SUM($E$32+$E$31+$E$33+$E$34+$E$35+$E$36+$E$37+$E$38+$E$39+$E$40+$E$41+$E$42+$E$43+$E$44+$E$45+$E$46+$E$47+$E$48+$E$49+$E$50) -> 63735 | G50: 95 | H50: =SUMIF(Returns!B:B, A50, Returns!P:P) -> 0 | I50: =SUMIF(Returns!B:B, A50, Returns!L:L) -> 0
A51: 45737 | B51: =SUMIF(Sales!A:A, A51, Sales!J:J) -> 8 | C51: =SUMIF(Sales!A:A, A51,Sales!M:M) -> 5255 | D51: =SUM($C$32+$C$31+$C$33+$C$34+$C$35+$C$36+$C$39+$C$37+$C$38+$C$40+$C$41+$C$42+$C$43+$C$44+$C$45+$C$46+$C$47+$C$48+$C$49+$C$50+$C$51) -> 104236.71 | E51: =SUMIF(Sales!A:A, A51, Sales!N:N) -> 3501 | F51: =SUM($E$32+$E$31+$E$33+$E$34+$E$35+$E$36+$E$37+$E$38+$E$39+$E$40+$E$41+$E$42+$E$43+$E$44+$E$45+$E$46+$E$47+$E$48+$E$49+$E$50+$E$51) -> 67236 | G51: 74 | H51: =SUMIF(Returns!B:B, A51, Returns!P:P) -> 0 | I51: =SUMIF(Returns!B:B, A51, Returns!L:L) -> 0
A52: 45738 | B52: =SUMIF(Sales!A:A, A52, Sales!J:J) -> 5 | C52: =SUMIF(Sales!A:A, A52,Sales!M:M) -> 2990 | D52: =SUM($C$32+$C$31+$C$33+$C$34+$C$35+$C$36+$C$39+$C$37+$C$38+$C$40+$C$41+$C$42+$C$43+$C$44+$C$45+$C$46+$C$47+$C$48+$C$49+$C$50+$C$51+$C$52) -> 107226.71 | E52: =SUMIF(Sales!A:A, A52, Sales!N:N) -> 1972 | F52: =SUM($E$32+$E$31+$E$33+$E$34+$E$35+$E$36+$E$37+$E$38+$E$39+$E$40+$E$41+$E$42+$E$43+$E$44+$E$45+$E$46+$E$47+$E$48+$E$49+$E$50+$E$51+$E$52) -> 69208 | G52: 112 | H52: =SUMIF(Returns!B:B, A52, Returns!P:P) -> 0 | I52: =SUMIF(Returns!B:B, A52, Returns!L:L) -> 0
A53: 45739 | B53: =SUMIF(Sales!A:A, A53, Sales!J:J) -> 9 | C53: =SUMIF(Sales!A:A, A53,Sales!M:M) -> 5068 | D53: =SUM($C$32+$C$31+$C$33+$C$34+$C$35+$C$36+$C$39+$C$37+$C$38+$C$40+$C$41+$C$42+$C$43+$C$44+$C$45+$C$46+$C$47+$C$48+$C$49+$C$50+$C$51+$C$52+C53) -> 112294.71 | E53: =SUMIF(Sales!A:A, A53, Sales!N:N) -> 3386 | F53: =SUM($E$32+$E$31+$E$33+$E$34+$E$35+$E$36+$E$37+$E$38+$E$39+$E$40+$E$41+$E$42+$E$43+$E$44+$E$45+$E$46+$E$47+$E$48+$E$49+$E$50+$E$51+$E$52+E53) -> 72594 | G53: 117 | H53: =SUMIF(Returns!B:B, A53, Returns!P:P) -> 0 | I53: =SUMIF(Returns!B:B, A53, Returns!L:L) -> 0
A54: 45740 | B54: =SUMIF(Sales!A:A, A54, Sales!J:J) -> 7 | C54: =SUMIF(Sales!A:A, A54,Sales!M:M) -> 3544 | D54: =SUM($C$32+$C$31+$C$33+$C$34+$C$35+$C$36+$C$39+$C$37+$C$38+$C$40+$C$41+$C$42+$C$43+$C$44+$C$45+$C$46+$C$47+$C$48+$C$49+$C$50+$C$51+$C$52+C54+C53) -> 115838.71 | E54: =SUMIF(Sales!A:A, A54, Sales!N:N) -> 2299 | F54: =SUM($E$32+$E$31+$E$33+$E$34+$E$35+$E$36+$E$37+$E$38+$E$39+$E$40+$E$41+$E$42+$E$43+$E$44+$E$45+$E$46+$E$47+$E$48+$E$49+$E$50+$E$51+$E$52+E54+E53) -> 74893 | G54: 74 | H54: =SUMIF(Returns!B:B, A54, Returns!P:P) -> 0 | I54: =SUMIF(Returns!B:B, A54, Returns!L:L) -> 0
A55: 45741 | B55: =SUMIF(Sales!A:A, A55, Sales!J:J) -> 6 | C55: =SUMIF(Sales!A:A, A55,Sales!M:M) -> 3019 | D55: =SUM($C$32+$C$31+$C$33+$C$34+$C$35+$C$36+$C$39+$C$37+$C$38+$C$40+$C$41+$C$42+$C$43+$C$44+$C$45+$C$46+$C$47+$C$48+$C$49+$C$50+$C$51+$C$52+C55+C54+C53) -> 118857.71 | E55: =SUMIF(Sales!A:A, A55, Sales!N:N) -> 1952 | F55: =SUM($E$32+$E$31+$E$33+$E$34+$E$35+$E$36+$E$37+$E$38+$E$39+$E$40+$E$41+$E$42+$E$43+$E$44+$E$45+$E$46+$E$47+$E$48+$E$49+$E$50+$E$51+$E$52+E55+E54+E53) -> 76845 | G55: 59 | H55: =SUMIF(Returns!B:B, A55, Returns!P:P) -> 0 | I55: =SUMIF(Returns!B:B, A55, Returns!L:L) -> 0
A56: 45742 | B56: =SUMIF(Sales!A:A, A56, Sales!J:J) -> 9 | C56: =SUMIF(Sales!A:A, A56,Sales!M:M) -> 4729 | D56: =SUM($C$32+$C$31+$C$33+$C$34+$C$35+$C$36+$C$39+$C$37+$C$38+$C$40+$C$41+$C$42+$C$43+$C$44+$C$45+$C$46+$C$47+$C$48+$C$49+$C$50+$C$51+$C$52+$C$56+$C$55+$C$54+$C$53) -> 123586.71 | E56: =SUMIF(Sales!A:A, A56, Sales!N:N) -> 3102 | F56: =SUM($E$32+$E$31+$E$33+$E$34+$E$35+$E$36+$E$37+$E$38+$E$39+$E$40+$E$41+$E$42+$E$43+$E$44+$E$45+$E$46+$E$47+$E$48+$E$49+$E$50+$E$51+$E$52+E56+E55+E54+$E$53) -> 79947 | G56: 40.5 | H56: =SUMIF(Returns!B:B, A56, Returns!P:P) -> 449 | I56: =SUMIF(Returns!B:B, A56, Returns!L:L) -> 1
A57: 45743 | B57: =SUMIF(Sales!A:A, A57, Sales!J:J) -> 3 | C57: =SUMIF(Sales!A:A, A57,Sales!M:M) -> 1448 | D57: =SUM($C$32+$C$31+$C$33+$C$34+$C$35+$C$36+$C$39+$C$37+$C$38+$C$40+$C$41+$C$42+$C$43+$C$44+$C$45+$C$46+$C$47+$C$48+$C$49+$C$50+$C$51+$C$52+$C$56+$C$55+$C$54+$C$53+$C$57) -> 125034.71 | E57: =SUMIF(Sales!A:A, A57, Sales!N:N) -> 918 | F57: =SUM($E$32+$E$31+$E$33+$E$34+$E$35+$E$36+$E$37+$E$38+$E$39+$E$40+$E$41+$E$42+$E$43+$E$44+$E$45+$E$46+$E$47+$E$48+$E$49+$E$50+$E$51+$E$52+$E$57+$E$56+$E$55+$E$53+$E$54) -> 80865 | G57: 77 | H57: =SUMIF(Returns!B:B, A57, Returns!P:P) -> 738 | I57: =SUMIF(Returns!B:B, A57, Returns!L:L) -> 2
A58: 45744 | B58: =SUMIF(Sales!A:A, A58, Sales!J:J) -> 6 | C58: =SUMIF(Sales!A:A, A58,Sales!M:M) -> 3525 | D58: =SUM($C$32+$C$31+$C$33+$C$34+$C$35+$C$36+$C$39+$C$37+$C$38+$C$40+$C$41+$C$42+$C$43+$C$44+$C$45+$C$46+$C$47+$C$48+$C$49+$C$50+$C$51+$C$52+$C$56+$C$55+$C$54+$C$53+$C$57+$C$58) -> 128559.71 | E58: =SUMIF(Sales!A:A, A58, Sales!N:N) -> 2311 | F58: =SUM($E$32+$E$31+$E$33+$E$34+$E$35+$E$36+$E$37+$E$38+$E$39+$E$40+$E$41+$E$42+$E$43+$E$44+$E$45+$E$46+$E$47+$E$48+$E$49+$E$50+$E$51+$E$52+$E$57+$E$56+$E$55+$E$53+$E$54+$E$585+$E$58) -> 83176 | G58: 132 | H58: =SUMIF(Returns!B:B, A58, Returns!P:P) -> 0 | I58: =SUMIF(Returns!B:B, A58, Returns!L:L) -> 0
A59: 45745 | B59: =SUMIF(Sales!A:A, A59, Sales!J:J) -> 4 | C59: =SUMIF(Sales!A:A, A59,Sales!M:M) -> 1859 | D59: =SUM($C$32+$C$31+$C$33+$C$34+$C$35+$C$36+$C$39+$C$37+$C$38+$C$40+$C$41+$C$42+$C$43+$C$44+$C$45+$C$46+$C$47+$C$48+$C$49+$C$50+$C$51+$C$52+$C$56+$C$55+$C$54+$C$53+$C$57+$C$58+$C$59) -> 130418.71 | E59: =SUMIF(Sales!A:A, A59, Sales!N:N) -> 1117 | F59: =SUM($E$32+$E$31+$E$33+$E$34+$E$35+$E$36+$E$37+$E$38+$E$39+$E$40+$E$41+$E$42+$E$43+$E$44+$E$45+$E$46+$E$47+$E$48+$E$49+$E$50+$E$51+$E$52+$E$57+$E$56+$E$55+$E$53+$E$54+$E$585+E58+$E$59) -> 84293 | G59: 137 | H59: =SUMIF(Returns!B:B, A59, Returns!P:P) -> 0 | I59: =SUMIF(Returns!B:B, A59, Returns!L:L) -> 0
A60: 45746 | B60: =SUMIF(Sales!A:A, A60, Sales!J:J) -> 4 | C60: =SUMIF(Sales!A:A, A60,Sales!M:M) -> 2508 | D60: =SUM($C$32+$C$31+$C$33+$C$34+$C$35+$C$36+$C$39+$C$37+$C$38+$C$40+$C$41+$C$42+$C$43+$C$44+$C$45+$C$46+$C$47+$C$48+$C$49+$C$50+$C$51+$C$52+$C$56+$C$55+$C$54+$C$53+$C$57+$C$58+$C$59+$C$60) -> 132926.71 | E60: =SUMIF(Sales!A:A, A60, Sales!N:N) -> 1618 | F60: =SUM($E$32+$E$31+$E$33+$E$34+$E$35+$E$36+$E$37+$E$38+$E$39+$E$40+$E$41+$E$42+$E$43+$E$44+$E$45+$E$46+$E$47+$E$48+$E$49+$E$50+$E$51+$E$52+$E$57+$E$56+$E$55+$E$53+$E$54+E$585+$E$59+$E$59+$E$58+$E$60) -> 87028 | G60: 137 | H60: =SUMIF(Returns!B:B, A60, Returns!P:P) -> 0 | I60: =SUMIF(Returns!B:B, A60, Returns!L:L) -> 0
A61: 45747 | B61: =SUMIF(Sales!A:A, A61, Sales!J:J) -> 9 | C61: =SUMIF(Sales!A:A, A61,Sales!M:M) -> 6096 | D61: =SUM($C$32+$C$31+$C$33+$C$34+$C$35+$C$36+$C$39+$C$37+$C$38+$C$40+$C$41+$C$42+$C$43+$C$44+$C$45+$C$46+$C$47+$C$48+$C$49+$C$50+$C$51+$C$52+$C$56+$C$55+$C$54+$C$53+$C$57+$C$58+$C$59+$C$60+$C$61) -> 139022.71 | E61: =SUMIF(Sales!A:A, A61, Sales!N:N) -> 4015 | F61: =SUM($E$32+$E$31+$E$33+$E$34+$E$35+$E$36+$E$37+$E$38+$E$39+$E$40+$E$41+$E$42+$E$43+$E$44+$E$45+$E$46+$E$47+$E$48+$E$49+$E$50+$E$51+$E$52+$E$57+$E$56+$E$55+$E$53+$E$54+E$585+$E$59+$E$59+$E$58+$E$60+$E$61) -> 91043 | G61: 272 | H61: =SUMIF(Returns!B:B, A61, Returns!P:P) -> 0 | I61: =SUMIF(Returns!B:B, A61, Returns!L:L) -> 0
A62: 45748 | B62: =SUMIF(Sales!A:A, A62, Sales!J:J) -> 10 | C62: =SUMIF(Sales!A:A, A62,Sales!M:M) -> 7560
D63: Target | E63: Achieved | F63: Gap | G63: Achieved (In %)
D64: 200000 | E64: =D94 -> 121157 | F64: =D64-E64 -> 78843 | G64: =E64/D64*1 -> 0.605785
A65: Date | B65: Order qty | C65: Order Value | D65: O_Total | E65: setlement | F65: S_Total | G65: Advertisment spend | H65: Returns | I65: Returns_Vol
A66: 45748 | B66: =SUMIF(Sales!A:A, A66, Sales!J:J) -> 10 | C66: =SUMIF(Sales!A:A, A66,Sales!M:M) -> 7560 | D66: =SUM(C66) -> 7560 | E66: =SUMIF(Sales!A:A, A66, Sales!N:N) -> 5054 | F66: =SUM(E66) -> 5054 | G66: 228 | H66: =SUMIF(Returns!B:B, A66, Returns!P:P) -> 930 | I66: =SUMIF(Returns!B:B, A66, Returns!L:L) -> 1
A67: 45749 | B67: =SUMIF(Sales!A:A, A67, Sales!J:J) -> 7 | C67: =SUMIF(Sales!A:A, A67,Sales!M:M) -> 3283 | D67: =SUM($C$67+$C$66) -> 10843 | E67: =SUMIF(Sales!A:A, A67, Sales!N:N) -> 2060 | F67: =SUM($E$67+$E$66) -> 7114 | G67: 202 | H67: =SUMIF(Returns!B:B, A67, Returns!P:P) -> 0 | I67: =SUMIF(Returns!B:B, A67, Returns!L:L) -> 0
A68: 45750 | B68: =SUMIF(Sales!A:A, A68, Sales!J:J) -> 8 | C68: =SUMIF(Sales!A:A, A68,Sales!M:M) -> 5044 | D68: =SUM($C$67+$C$66+$C$68) -> 15887 | E68: =SUMIF(Sales!A:A, A68, Sales!N:N) -> 3235 | F68: =SUM($E$67+$E$66+$E$68) -> 10349 | G68: 132 | H68: =SUMIF(Returns!B:B, A68, Returns!P:P) -> 0 | I68: =SUMIF(Returns!B:B, A68, Returns!L:L) -> 0
A69: 45751 | B69: =SUMIF(Sales!A:A, A69, Sales!J:J) -> 2 | C69: =SUMIF(Sales!A:A, A69,Sales!M:M) -> 1444 | D69: =SUM($C$67+$C$66+$C$68+$C$69) -> 17331 | E69: =SUMIF(Sales!A:A, A69, Sales!N:N) -> 944 | F69: =SUM($E$67+$E$66+$E$68+$E$69) -> 11293 | G69: 41 | H69: =SUMIF(Returns!B:B, A69, Returns!P:P) -> 0 | I69: =SUMIF(Returns!B:B, A69, Returns!L:L) -> 0
A70: 45752 | B70: =SUMIF(Sales!A:A, A70, Sales!J:J) -> 9 | C70: =SUMIF(Sales!A:A, A70,Sales!M:M) -> 3855 | D70: =SUM($C$67+$C$66+$C$68+$C$69+$C$70) -> 21186 | E70: =SUMIF(Sales!A:A, A70, Sales!N:N) -> 2259 | F70: =SUM($E$67+$E$66+$E$68+$E$69+$E$70) -> 13552 | G70: 104 | H70: =SUMIF(Returns!B:B, A70, Returns!P:P) -> 0 | I70: =SUMIF(Returns!B:B, A70, Returns!L:L) -> 0
A71: 45753 | B71: =SUMIF(Sales!A:A, A71, Sales!J:J) -> 2 | C71: =SUMIF(Sales!A:A, A71,Sales!M:M) -> 1699 | D71: =SUM(C66:C71) -> 22885 | E71: =SUMIF(Sales!A:A, A71, Sales!N:N) -> 1328 | F71: =SUM($E$67+$E$66+$E$68+$E$69+$E$70+$E$71) -> 14880 | G71: 110 | H71: =SUMIF(Returns!B:B, A71, Returns!P:P) -> 0 | I71: =SUMIF(Returns!B:B, A71, Returns!L:L) -> 0
A72: 45754 | B72: =SUMIF(Sales!A:A, A72, Sales!J:J) -> 7 | C72: =SUMIF(Sales!A:A, A72,Sales!M:M) -> 3726 | D72: =SUM(C66:C72) -> 26611 | E72: =SUMIF(Sales!A:A, A72, Sales!N:N) -> 2391 | F72: =SUM($E$67+$E$66+$E$68+$E$69+$E$70+$E$71+$E$72) -> 17271 | G72: 106 | H72: =SUMIF(Returns!B:B, A72, Returns!P:P) -> 0 | I72: =SUMIF(Returns!B:B, A72, Returns!L:L) -> 0
A73: 45755 | B73: =SUMIF(Sales!A:A, A73, Sales!J:J) -> 13 | C73: =SUMIF(Sales!A:A, A73,Sales!M:M) -> 7116 | D73: =SUM(C66:C73) -> 33727 | E73: =SUMIF(Sales!A:A, A73, Sales!N:N) -> 4501 | F73: =SUM($E$67+$E$66+$E$68+$E$69+$E$70+$E$71+$E$72+E73) -> 21772 | G73: 63 | H73: =SUMIF(Returns!B:B, A73, Returns!P:P) -> 1879 | I73: =SUMIF(Returns!B:B, A73, Returns!L:L) -> 2
A74: 45756 | B74: =SUMIF(Sales!A:A, A74, Sales!J:J) -> 4 | C74: =SUMIF(Sales!A:A, A74,Sales!M:M) -> 2096 | D74: =SUM(C66:C74) -> 35823 | E74: =SUMIF(Sales!A:A, A74, Sales!N:N) -> 1349 | F74: =SUM(E$67+E$66+E$68+E$69+E$70+E$71+E$72+E$74+E$73) -> 23121 | G74: 95 | H74: =SUMIF(Returns!B:B, A74, Returns!P:P) -> 0 | I74: =SUMIF(Returns!B:B, A74, Returns!L:L) -> 0
A75: 45757 | B75: =SUMIF(Sales!A:A, A75, Sales!J:J) -> 9 | C75: =SUMIF(Sales!A:A, A75,Sales!M:M) -> 5588 | D75: =SUM(C66:C75) -> 41411 | E75: =SUMIF(Sales!A:A, A75, Sales!N:N) -> 3620 | F75: =SUM(E$67+E$66+E$68+E$69+E$70+E$71+E$72+E$74+E$73+$E$75) -> 26741 | G75: 101 | H75: =SUMIF(Returns!B:B, A75, Returns!P:P) -> 0 | I75: =SUMIF(Returns!B:B, A75, Returns!L:L) -> 0
A76: 45758 | B76: =SUMIF(Sales!A:A, A76, Sales!J:J) -> 4 | C76: =SUMIF(Sales!A:A, A76,Sales!M:M) -> 1677 | D76: =SUM(C66:C76) -> 43088 | E76: =SUMIF(Sales!A:A, A76, Sales!N:N) -> 1010 | F76: =SUM(E$67+E$66+E$68+E$69+E$70+E$71+E$72+E$74+E$73+$E$75+E76) -> 27751 | G76: 103 | H76: =SUMIF(Returns!B:B, A76, Returns!P:P) -> 0 | I76: =SUMIF(Returns!B:B, A76, Returns!L:L) -> 0
A77: 45759 | B77: =SUMIF(Sales!A:A, A77, Sales!J:J) -> 2 | C77: =SUMIF(Sales!A:A, A77,Sales!M:M) -> 1284 | D77: =SUM(C66:C77) -> 44372 | E77: =SUMIF(Sales!A:A, A77, Sales!N:N) -> 858 | F77: =SUM($E67+$E66+$E68+$E69+$E70+$E71+$E72+$E74+$E73+$E75+$E77+$E76) -> 28609 | G77: 137 | H77: =SUMIF(Returns!B:B, A77, Returns!P:P) -> 0 | I77: =SUMIF(Returns!B:B, A77, Returns!L:L) -> 0
A78: 45760 | B78: =SUMIF(Sales!A:A, A78, Sales!J:J) -> 7 | C78: =SUMIF(Sales!A:A, A78,Sales!M:M) -> 4511 | D78: =SUM(C66:C78) -> 48883 | E78: =SUMIF(Sales!A:A, A78, Sales!N:N) -> 2922 | F78: =SUM($E67+$E66+$E68+$E69+$E70+$E71+$E72+$E74+$E73+$E75+$E78+$E77+$E76) -> 31531 | G78: 331 | H78: =SUMIF(Returns!B:B, A78, Returns!P:P) -> 0 | I78: =SUMIF(Returns!B:B, A78, Returns!L:L) -> 0
A79: 45761 | B79: =SUMIF(Sales!A:A, A79, Sales!J:J) -> 6 | C79: =SUMIF(Sales!A:A, A79,Sales!M:M) -> 2775 | D79: =SUM(C66:C79) -> 51658 | E79: =SUMIF(Sales!A:A, A79, Sales!N:N) -> 1718 | F79: =SUM($E68+$E67+$E69+$E70+$E71+$E72+$E73+$E75+$E74+$E76+$E79+$E78+$E77+$E$66) -> 33249 | G79: 266 | H79: =SUMIF(Returns!B:B, A79, Returns!P:P) -> 0 | I79: =SUMIF(Returns!B:B, A79, Returns!L:L) -> 0
A80: 45762 | B80: =SUMIF(Sales!A:A, A80, Sales!J:J) -> 16 | C80: =SUMIF(Sales!A:A, A80,Sales!M:M) -> 6549 | D80: =SUM(C66:C80) -> 58207 | E80: =SUMIF(Sales!A:A, A80, Sales!N:N) -> 4573 | F80: =SUM(E66:E80) -> 37822 | G80: 149 | H80: =SUMIF(Returns!B:B, A80, Returns!P:P) -> 0 | I80: =SUMIF(Returns!B:B, A80, Returns!L:L) -> 0
A81: 45763 | B81: =SUMIF(Sales!A:A, A81, Sales!J:J) -> 4 | C81: =SUMIF(Sales!A:A, A81,Sales!M:M) -> 1776 | D81: =SUM(C66:C81) -> 59983 | E81: =SUMIF(Sales!A:A, A81, Sales!N:N) -> 1148 | F81: =SUM(E66:E81) -> 38970 | G81: 276 | H81: =SUMIF(Returns!B:B, A81, Returns!P:P) -> 0 | I81: =SUMIF(Returns!B:B, A81, Returns!L:L) -> 0
A82: 45764 | B82: =SUMIF(Sales!A:A, A82, Sales!J:J) -> 8 | C82: =SUMIF(Sales!A:A, A82,Sales!M:M) -> 5232 | D82: =SUM(C66:C82) -> 65215 | E82: =SUMIF(Sales!A:A, A82, Sales!N:N) -> 3372 | F82: =SUM(E66:E82) -> 42342 | G82: 166 | H82: =SUMIF(Returns!B:B, A82, Returns!P:P) -> 0 | I82: =SUMIF(Returns!B:B, A82, Returns!L:L) -> 0
A83: 45765 | B83: =SUMIF(Sales!A:A, A83, Sales!J:J) -> 6 | C83: =SUMIF(Sales!A:A, A83,Sales!M:M) -> 2463 | D83: =SUM(C66:C83) -> 67678 | E83: =SUMIF(Sales!A:A, A83, Sales!N:N) -> 1522 | F83: =SUM(E66:E83) -> 43864 | G83: 101 | H83: =SUMIF(Returns!B:B, A83, Returns!P:P) -> 0 | I83: =SUMIF(Returns!B:B, A83, Returns!L:L) -> 0
A84: 45766 | B84: =SUMIF(Sales!A:A, A84, Sales!J:J) -> 4 | C84: =SUMIF(Sales!A:A, A84,Sales!M:M) -> 2626 | D84: =SUM(C66:C84) -> 70304 | E84: =SUMIF(Sales!A:A, A84, Sales!N:N) -> 1873 | F84: =SUM(E66:E84) -> 45737 | G84: 139 | H84: =SUMIF(Returns!B:B, A84, Returns!P:P) -> 0 | I84: =SUMIF(Returns!B:B, A84, Returns!L:L) -> 0
A85: 45767 | B85: =SUMIF(Sales!A:A, A85, Sales!J:J) -> 6 | C85: =SUMIF(Sales!A:A, A85,Sales!M:M) -> 4603 | D85: =SUM(C66:C85) -> 74907 | E85: =SUMIF(Sales!A:A, A85, Sales!N:N) -> 3128 | F85: =SUM(E66:E85) -> 48865 | G85: 53 | H85: =SUMIF(Returns!B:B, A85, Returns!P:P) -> 0 | I85: =SUMIF(Returns!B:B, A85, Returns!L:L) -> 0
A86: 45768 | B86: =SUMIF(Sales!A:A, A86, Sales!J:J) -> 13 | C86: =SUMIF(Sales!A:A, A86,Sales!M:M) -> 7997 | D86: =SUM(C66:C86) -> 82904 | E86: =SUMIF(Sales!A:A, A86, Sales!N:N) -> 5381 | F86: =SUM(E66:E86) -> 54246 | G86: 219 | H86: =SUMIF(Returns!B:B, A86, Returns!P:P) -> 0 | I86: =SUMIF(Returns!B:B, A86, Returns!L:L) -> 0
A87: 45769 | B87: =SUMIF(Sales!A:A, A87, Sales!J:J) -> 8 | C87: =SUMIF(Sales!A:A, A87,Sales!M:M) -> 4485 | D87: =SUM(C66:C87) -> 87389 | E87: =SUMIF(Sales!A:A, A87, Sales!N:N) -> 3195 | F87: =SUM(E66:E87) -> 57441 | G87: 227 | H87: =SUMIF(Returns!B:B, A87, Returns!P:P) -> 0 | I87: =SUMIF(Returns!B:B, A87, Returns!L:L) -> 0
A88: 45770 | B88: =SUMIF(Sales!A:A, A88, Sales!J:J) -> 9 | C88: =SUMIF(Sales!A:A, A88,Sales!M:M) -> 2897 | D88: =SUM(C66:C88) -> 90286 | E88: =SUMIF(Sales!A:A, A88, Sales!N:N) -> 1945 | F88: =SUM(E66:E88) -> 59386 | G88: 222 | H88: =SUMIF(Returns!B:B, A88, Returns!P:P) -> 0 | I88: =SUMIF(Returns!B:B, A88, Returns!L:L) -> 0
A89: 45771 | B89: =SUMIF(Sales!A:A, A89, Sales!J:J) -> 8 | C89: =SUMIF(Sales!A:A, A89,Sales!M:M) -> 4225 | D89: =SUM(C66:C89) -> 94511 | E89: =SUMIF(Sales!A:A, A89, Sales!N:N) -> 2939 | F89: =SUM(E66:E89) -> 62325 | G89: 136 | H89: =SUMIF(Returns!B:B, A89, Returns!P:P) -> 0 | I89: =SUMIF(Returns!B:B, A89, Returns!L:L) -> 0
A90: 45772 | B90: =SUMIF(Sales!A:A, A90, Sales!J:J) -> 9 | C90: =SUMIF(Sales!A:A, A90,Sales!M:M) -> 6747 | D90: =SUM(C66:C90) -> 101258 | E90: =SUMIF(Sales!A:A, A90, Sales!N:N) -> 4732 | F90: =SUM(E66:E90) -> 67057 | G90: 90 | H90: =SUMIF(Returns!B:B, A90, Returns!P:P) -> 0 | I90: =SUMIF(Returns!B:B, A90, Returns!L:L) -> 0
A91: 45773 | B91: =SUMIF(Sales!A:A, A91, Sales!J:J) -> 8 | C91: =SUMIF(Sales!A:A, A91,Sales!M:M) -> 3608 | D91: =SUM(C66:C91) -> 104866 | E91: =SUMIF(Sales!A:A, A91, Sales!N:N) -> 2411 | F91: =SUM(E66:E91) -> 69468 | G91: 173 | H91: =SUMIF(Returns!B:B, A91, Returns!P:P) -> 0 | I91: =SUMIF(Returns!B:B, A91, Returns!L:L) -> 0
A92: 45774 | B92: =SUMIF(Sales!A:A, A92, Sales!J:J) -> 10 | C92: =SUMIF(Sales!A:A, A92,Sales!M:M) -> 6656 | D92: =SUM(C66:C92) -> 111522 | E92: =SUMIF(Sales!A:A, A92, Sales!N:N) -> 4728 | F92: =SUM(E66:E92) -> 74196 | G92: 164 | H92: =SUMIF(Returns!B:B, A92, Returns!P:P) -> 0 | I92: =SUMIF(Returns!B:B, A92, Returns!L:L) -> 0
A93: 45775 | B93: =SUMIF(Sales!A:A, A93, Sales!J:J) -> 9 | C93: =SUMIF(Sales!A:A, A93,Sales!M:M) -> 5158 | D93: =SUM(C66:C93) -> 116680 | E93: =SUMIF(Sales!A:A, A93, Sales!N:N) -> 3593 | F93: =SUM(E66:E93) -> 77789 | G93: 121 | H93: =SUMIF(Returns!B:B, A93, Returns!P:P) -> 0 | I93: =SUMIF(Returns!B:B, A93, Returns!L:L) -> 0
A94: 45776 | B94: =SUMIF(Sales!A:A, A94, Sales!J:J) -> 7 | C94: =SUMIF(Sales!A:A, A94,Sales!M:M) -> 4477 | D94: =SUM(C66:C94) -> 121157 | E94: =SUMIF(Sales!A:A, A94, Sales!N:N) -> 3198 | F94: =SUM(E66:E94) -> 80987 | G94: 121 | H94: =SUMIF(Returns!B:B, A94, Returns!P:P) -> 0 | I94: =SUMIF(Returns!B:B, A94, Returns!L:L) -> 0
A95: 45777

Sheet Ads_Cost
A1: Date | B1: Platforms | C1: Spent | D1: Sales | E1: Order Tpe | F1: Orders | G1: ROAS | H1: ACOS | I1: Clicks | J1: CTR | K1: Impressions | L1: CPC
A2: 45668 | B2: Amazon | C2: 21.24 | D2: 0 | E2: Paid | F2: 0 | G2: 0 | H2: 0 | I2: 2 | J2: =I2/K2 -> 0.0081300813 | K2: 246 | L2: =Ads_Cost!$C2/Ads_Cost!$I2 -> 10.62
A3: 45669 | B3: Amazon | C3: 70.57 | D3: 250 | E3: Paid | F3: 1 | G3: =D3/C3 -> 3.5425818 | H3: =C3/D3 -> 0.28228 | I3: 7 | J3: =I3/K3 -> 0.01594533 | K3: 439 | L3: =Ads_Cost!$C3/Ads_Cost!$I3 -> 10.081429
A4: 45670 | B4: Amazon | C4: 28.54 | D4: 0 | E4: Paid | F4: 0 | G4: =D4/C4 -> 0 | H4: =IF(Ads_Cost!$D4=0, 0, (Ads_Cost!$C4/Ads_Cost!$D4)*1) -> 0 | I4: 5 | J4: =I4/K4 -> 0.014164306 | K4: 353 | L4: =Ads_Cost!$C4/Ads_Cost!$I4 -> 5.708
A5: 45671 | B5: Amazon | C5: 17.7 | D5: 494.07 | E5: Paid | F5: 2 | G5: =IF(Ads_Cost!$C5=0, 0, Ads_Cost!$D5/Ads_Cost!$C5) -> 27.913559 | H5: =IF(Ads_Cost!$D5=0, 0, (Ads_Cost!$C5/Ads_Cost!$D5)*1) -> 0.035824883 | I5: 2 | J5: =IF(Ads_Cost!$D5=0, 0, (Ads_Cost!$C5/Ads_Cost!$D5)*1) -> 0.035824883 | K5: 277 | L5: =IF(Ads_Cost!$I5=0, 0, Ads_Cost!$C5/Ads_Cost!$I5) -> 8.85
A6: 45672 | B6: Amazon | C6: 21.15 | D6: 0 | E6: Paid | F6: 0 | G6: =IF(Ads_Cost!$C6=0, 0, Ads_Cost!$D6/Ads_Cost!$C6) -> 0 | H6: =IF(Ads_Cost!$D6=0, 0, (Ads_Cost!$C6/Ads_Cost!$D6)*1) -> 0 | I6: 2 | J6: =IF(Ads_Cost!$D6=0, 0, (Ads_Cost!$C6/Ads_Cost!$D6)*1) -> 0 | K6: 345 | L6: =IF(Ads_Cost!$I6=0, 0, Ads_Cost!$C6/Ads_Cost!$I6) -> 10.575
A7: 45673 | B7: Amazon | C7: 42.57 | D7: 0 | E7: Paid | F7: 0 | G7: =IF(Ads_Cost!$C7=0, 0, Ads_Cost!$D7/Ads_Cost!$C7) -> 0 | H7: =IF(Ads_Cost!$D7=0, 0, (Ads_Cost!$C7/Ads_Cost!$D7)*1) -> 0 | I7: 6 | J7: =IF(Ads_Cost!$D7=0, 0, (Ads_Cost!$C7/Ads_Cost!$D7)*1) -> 0 | K7: 352 | L7: =IF(Ads_Cost!$I7=0, 0, Ads_Cost!$C7/Ads_Cost!$I7) -> 7.095
A8: 45674 | B8: Amazon | C8: 255.98 | D8: 0 | E8: Paid | F8: 0 | G8: =IF(Ads_Cost!$C8=0, 0, Ads_Cost!$D8/Ads_Cost!$C8) -> 0 | H8: =IF(Ads_Cost!$D8=0, 0, (Ads_Cost!$C8/Ads_Cost!$D8)*1) -> 0 | I8: 17 | J8: =I8/K8 -> 0.013178295 | K8: 1290 | L8: =Ads_Cost!$C8/Ads_Cost!$I8 -> 15.057647
A9: 45675 | B9: Amazon | C9: 131.57 | D9: 0 | E9: Paid | F9: 0 | G9: =IF(Ads_Cost!$C9=0, 0, Ads_Cost!$D9/Ads_Cost!$C9) -> 0 | H9: =IF(Ads_Cost!$D9=0, 0, (Ads_Cost!$C9/Ads_Cost!$D9)*1) -> 0 | I9: 14 | J9: =I9/K9 -> 0.023294509 | K9: 601 | L9: =Ads_Cost!$C9/Ads_Cost!$I9 -> 9.3978571
A10: 45676 | B10: Amazon | C10: 274.53 | D10: 211.02 | E10: Paid | F10: 1 | G10: =IF(Ads_Cost!$C10=0, 0, Ads_Cost!$D10/Ads_Cost!$C10) -> 0.76865916 | H10: =IF(Ads_Cost!$D10=0, 0, (Ads_Cost!$C10/Ads_Cost!$D10)*1) -> 1.3009667 | I10: 32 | J10: =I10/K10 -> 0.015009381 | K10: 2132 | L10: =Ads_Cost!$C10/Ads_Cost!$I10 -> 8.5790625
A11: 45677 | B11: Amazon | C11: 373.06 | D11: 844.92 | E11: Paid | F11: 2 | G11: =IF(Ads_Cost!$C11=0, 0, Ads_Cost!$D11/Ads_Cost!$C11) -> 2.2648368 | H11: =IF(Ads_Cost!$D11=0, 0, (Ads_Cost!$C11/Ads_Cost!$D11)*1) -> 0.44153293 | I11: 46 | J11: =I11/K11 -> 0.012791991 | K11: 3596 | L11: =Ads_Cost!$C11/Ads_Cost!$I11 -> 8.11
A12: 45678 | B12: Amazon | C12: 213.4 | D12: 211.02 | E12: Paid | F12: 1 | G12: =IF(Ads_Cost!$C12=0, 0, Ads_Cost!$D12/Ads_Cost!$C12) -> 0.98884724 | H12: =IF(Ads_Cost!$D12=0, 0, (Ads_Cost!$C12/Ads_Cost!$D12)*1) -> 1.0112786 | I12: 25 | J12: =I12/K12 -> 0.010775862 | K12: 2320 | L12: =Ads_Cost!$C12/Ads_Cost!$I12 -> 8.536
A13: 45679 | B13: Amazon | C13: 323.6 | D13: 0 | E13: Paid | F13: 0 | G13: =IF(Ads_Cost!$C13=0, 0, Ads_Cost!$D13/Ads_Cost!$C13) -> 0 | H13: =IF(Ads_Cost!$D13=0, 0, (Ads_Cost!$C13/Ads_Cost!$D13)*1) -> 0 | I13: 21 | J13: =I13/K13 -> 0.0025414498 | K13: 8263 | L13: =Ads_Cost!$C13/Ads_Cost!$I13 -> 15.409524
A14: 45680 | B14: Amazon | C14: 269.52 | D14: 0 | E14: Paid | F14: 0 | G14: =IF(Ads_Cost!$C14=0, 0, Ads_Cost!$D14/Ads_Cost!$C14) -> 0 | H14: =IF(Ads_Cost!$D14=0, 0, (Ads_Cost!$C14/Ads_Cost!$D14)*1) -> 0 | I14: 27 | J14: =I14/K14 -> 0.0050037064 | K14: 5396 | L14: =Ads_Cost!$C14/Ads_Cost!$I14 -> 9.9822222
A15: 45681 | B15: Amazon | C15: 119.08 | D15: 219.49 | E15: Paid | F15: 1 | G15: =IF(Ads_Cost!$C15=0, 0, Ads_Cost!$D15/Ads_Cost!$C15) -> 1.8432146 | H15: =IF(Ads_Cost!$D15=0, 0, (Ads_Cost!$C15/Ads_Cost!$D15)*1) -> 0.54253041 | I15: 16 | J15: =I15/K15 -> 0.004295302 | K15: 3725 | L15: =Ads_Cost!$C15/Ads_Cost!$I15 -> 7.4425
A16: 45682 | B16: Amazon | C16: 210.21 | D16: 0 | E16: Paid | F16: 0 | G16: =IF(Ads_Cost!$C16=0, 0, Ads_Cost!$D16/Ads_Cost!$C16) -> 0 | H16: =IF(Ads_Cost!$D16=0, 0, (Ads_Cost!$C16/Ads_Cost!$D16)*1) -> 0 | I16: 30 | J16: =I16/K16 -> 0.010642072 | K16: 2819 | L16: =Ads_Cost!$C16/Ads_Cost!$I16 -> 7.007
A17: 45683 | B17: Amazon | C17: 208.69 | D17: 0 | E17: Paid | F17: 0 | G17: =IF(Ads_Cost!$C17=0, 0, Ads_Cost!$D17/Ads_Cost!$C17) -> 0 | H17: =IF(Ads_Cost!$D17=0, 0, (Ads_Cost!$C17/Ads_Cost!$D17)*1) -> 0 | I17: 35 | J17: =I17/K17 -> 0.016233766 | K17: 2156 | L17: =Ads_Cost!$C17/Ads_Cost!$I17 -> 5.9625714
A18: 45684 | B18: Amazon | C18: 168.36 | D18: 643.22 | E18: Paid | F18: 1 | G18: =IF(Ads_Cost!$C18=0, 0, Ads_Cost!$D18/Ads_Cost!$C18) -> 3.8205037 | H18: =IF(Ads_Cost!$D18=0, 0, (Ads_Cost!$C18/Ads_Cost!$D18)*1) -> 0.26174559 | I18: 31 | J18: =I18/K18 -> 0.0039677461 | K18: 7813 | L18: =Ads_Cost!$C18/Ads_Cost!$I18 -> 5.4309677
A19: 45685 | B19: Amazon | C19: 283.36 | D19: 732.21 | E19: Paid | F19: 2 | G19: =IF(Ads_Cost!$C19=0, 0, Ads_Cost!$D19/Ads_Cost!$C19) -> 2.5840274 | H19: =IF(Ads_Cost!$D19=0, 0, (Ads_Cost!$C19/Ads_Cost!$D19)*1) -> 0.3869928 | I19: 64 | J19: =I19/K19 -> 0.0034296126 | K19: 18661 | L19: =Ads_Cost!$C19/Ads_Cost!$I19 -> 4.4275
... A97: 45763 | B97: Amazon | C97: 276.47 | D97: 1502.85 | E97: Paid | F97: 2 | G97: =IF(Ads_Cost!$C97=0, 0, Ads_Cost!$D97/Ads_Cost!$C97) -> 5.435852 | H97: =IF(Ads_Cost!$D97=0, 0, (Ads_Cost!$C97/Ads_Cost!$D97)*1) -> 0.1839638 | I97: 52 | J97: =I97/K97 -> 0.0053191489 | K97: 9776 | L97: =Ads_Cost!$C97/Ads_Cost!$I97 -> 5.3167308
A98: 45764 | B98: Amazon | E98: Paid | G98: =IF(Ads_Cost!$C98=0, 0, Ads_Cost!$D98/Ads_Cost!$C98) -> 0 | H98: =IF(Ads_Cost!$D98=0, 0, (Ads_Cost!$C98/Ads_Cost!$D98)*1) -> 0 | J98: =I98/K98 -> #DIV/0! | L98: =Ads_Cost!$C98/Ads_Cost!$I98 -> #DIV/0!
A99: 45765 | B99: Amazon | E99: Paid | G99: =IF(Ads_Cost!$C99=0, 0, Ads_Cost!$D99/Ads_Cost!$C99) -> 0 | H99: =IF(Ads_Cost!$D99=0, 0, (Ads_Cost!$C99/Ads_Cost!$D99)*1) -> 0 | J99: =I99/K99 -> #DIV/0! | L99: =Ads_Cost!$C99/Ads_Cost!$I99 -> #DIV/0!
A100: 45766 | B100: Amazon | E100: Paid | G100: =IF(Ads_Cost!$C100=0, 0, Ads_Cost!$D100/Ads_Cost!$C100) -> 0 | H100: =IF(Ads_Cost!$D100=0, 0, (Ads_Cost!$C100/Ads_Cost!$D100)*1) -> 0 | J100: =I100/K100 -> #DIV/0! | L100: =Ads_Cost!$C100/Ads_Cost!$I100 -> #DIV/0!
A101: 45767 | B101: Amazon | E101: Paid | G101: =IF(Ads_Cost!$C101=0, 0, Ads_Cost!$D101/Ads_Cost!$C101) -> 0 | H101: =IF(Ads_Cost!$D101=0, 0, (Ads_Cost!$C101/Ads_Cost!$D101)*1) -> 0 | J101: =I101/K101 -> #DIV/0! | L101: =Ads_Cost!$C101/Ads_Cost!$I101 -> #DIV/0!
A102: 45768 | B102: Amazon | E102: Paid | G102: =IF(Ads_Cost!$C102=0, 0, Ads_Cost!$D102/Ads_Cost!$C102) -> 0 | H102: =IF(Ads_Cost!$D102=0, 0, (Ads_Cost!$C102/Ads_Cost!$D102)*1) -> 0 | J102: =I102/K102 -> #DIV/0! | L102: =Ads_Cost!$C102/Ads_Cost!$I102 -> #DIV/0!
A103: 45769 | B103: Amazon | E103: Paid | G103: =IF(Ads_Cost!$C103=0, 0, Ads_Cost!$D103/Ads_Cost!$C103) -> 0 | H103: =IF(Ads_Cost!$D103=0, 0, (Ads_Cost!$C103/Ads_Cost!$D103)*1) -> 0 | L103: =Ads_Cost!$C103/Ads_Cost!$I103 -> #DIV/0!
A104: 45770
A105: 45771
A106: 45772
A107: 45773
A108: 45774
A109: 45775
A110: 45776
A111: 45777
A112: 45778
A113: 45779
A114: 45780
A115: 45781
... A130: 45796

Sheet Customer_Insights
A1: Date | B1: Platforms | C1: Product Name | D1: Product ID | E1: Feedbacks | F1: Rating
A2: 45701 | B2: Amazon | C2: Zody Diaper | D2: ZODY DIAPER-3PCS-S1 | E2: Best diaper till now I have used.packaging is so pretty and cloth is so soft | F2: 5
A3: 45702 | B3: Amazon | C3: Zody Diaper | D3: ZODY DIAPER - NVYBLU | E3: Great quality and very soft! | F3: 5
A4: 45703 | B4: Amazon | C4: Feeding Bed | D4: FEEDING BED-RED&WT | E4: Comfortable and easy to clean. | F4: 4
A5: 45704 | B5: Amazon | C5: Jabala Mist | D5: JABALA MIST-5PCS- 0-3M | E5: Smells amazing and lasts long! | F5: 5
A6: 45705 | B6: Amazon | C6: Diaper Pad | D6: DIAPER PAD-3PCS | E6: Absorbent and good material. | F6: 4
A7: 45706 | B7: Amazon | C7: Jabala Wings | D7: JABALA WINGS-5PCS- 0-3M-S1 | E7: Soft and comfortable for babies. | F7: 5
A8: 45707 | B8: Amazon | C8: Dry Sheet (L) | D8: DRY SHEET-SKY-S | E8: Perfect for overnight use. | F8: 4
A9: 45708 | B9: Amazon | C9: Kang De Bed | D9: KANG DE BED-ROSE | E9: Sturdy and comfortable. | F9: 5
A10: 45709 | B10: Amazon | C10: Pluto Bed Cradle | E10: Nice design and very safe. | F10: 4

Sheet Returns
A1: Order_Date | B1: Delivery_Date | C1: Quarter | D1: Locations | E1: Platforms | F1: Fullfilled_By | G1: Product Name | H1: Product_ID | I1: Return_Type | J1: Return_Reason | K1: Product_Condition | L1: Return_Qty | M1: Order_Qty | N1: Return_Volume | O1: Order_Volume | P1: Refund_Amount | Q1: Resllable_Qty | R1: Safe-T Claim | S1: Order_Amount
A2: 45690 | B2: 45696 | C2: ="Q" & CHOOSE(MONTH(Returns!$A2), "1", "1", "1", "2", "2", "2", "3", "3", "3", "4", "4", "4") & "_" & YEAR(Returns!$A2) -> Q1_2025 | D2: Kerala | E2: Amazon | F2: MFN | G2: Jabala Wings | H2: JABALA WINGS-6PCS- 3-6M-S2 | I2: C-Returns | J2: AMZ-PG-APP-TOO-SMALL | K2: Damaged | L2: 1 | M2: 1 | N2: 6 | O2: 6 | P2: 349 | R2: 0 | S2: 349
A3: 45681 | B3: 45698 | C3: ="Q" & CHOOSE(MONTH(Returns!$A3), "1", "1", "1", "2", "2", "2", "3", "3", "3", "4", "4", "4") & "_" & YEAR(Returns!$A3) -> Q1_2025 | D3: Maharashtra | E3: Amazon | F3: MFN | G3: Zody Diaper | H3: ZODY DIAPER-MC5 | I3: Rejected | J3: UND-UNKNOWN | K3: Damaged | L3: 1 | M3: 1 | N3: 1 | O3: 1 | P3: 299 | R3: 0 | S3: 299
A4: 45688 | B4: 45701 | C4: ="Q" & CHOOSE(MONTH(Returns!$A4), "1", "1", "1", "2", "2", "2", "3", "3", "3", "4", "4", "4") & "_" & YEAR(Returns!$A4) -> Q1_2025 | D4: Maharashtra | E4: Amazon | F4: MFN | G4: Zody Diaper | H4: ZODY DIAPER-MC4 | I4: Rejected | J4: UND-UNKNOWN | K4: Box Damaged | L4: 1 | M4: 1 | N4: 1 | O4: 1 | P4: 279 | R4: 55.7 | S4: 279
A5: 45688 | B5: 45701 | C5: ="Q" & CHOOSE(MONTH(Returns!$A5), "1", "1", "1", "2", "2", "2", "3", "3", "3", "4", "4", "4") & "_" & YEAR(Returns!$A5) -> Q1_2025 | D5: N/A | E5: meesho | F5: MFN | G5: Dry Sheet (S) | H5: DRY SHEET-SKY-S | I5: Rejected | J5: UND-UNKNOWN | K5: Good | L5: 1 | M5: 1 | N5: 1 | O5: 1 | P5: 179 | R5: 0 | S5: 179
A6: 45687 | B6: 45701 | C6: ="Q" & CHOOSE(MONTH(Returns!$A6), "1", "1", "1", "2", "2", "2", "3", "3", "3", "4", "4", "4") & "_" & YEAR(Returns!$A6) -> Q1_2025 | D6: N/A | E6: meesho | F6: MFN | G6: Dry Sheet (S) | H6: DRY SHEET-SKY-S | I6: Rejected | J6: UND-UNKNOWN | K6: Good | L6: 1 | M6: 1 | N6: 1 | O6: 1 | P6: 179 | R6: 0 | S6: 179
A7: 45687 | B7: 45705 | C7: ="Q" & CHOOSE(MONTH(Returns!$A7), "1", "1", "1", "2", "2", "2", "3", "3", "3", "4", "4", "4") & "_" & YEAR(Returns!$A7) -> Q1_2025 | D7: Rajasthan | E7: Amazon | F7: MFN | G7: Kang De Bed | H7: KANG DE BED-ROSE | I7: Rejected | J7: UND-UNKNOWN | K7: Good | L7: 1 | M7: 1 | N7: 1 | O7: 1 | P7: 635 | R7: 0 | S7: 635
A8: 45687 | B8: 45707 | C8: ="Q" & CHOOSE(MONTH(Returns!$A8), "1", "1", "1", "2", "2", "2", "3", "3", "3", "4", "4", "4") & "_" & YEAR(Returns!$A8) -> Q1_2025 | D8: N/A | E8: meesho | F8: MFN | G8: Dry Sheet (S) | H8: DRY SHEET-SKY-S | I8: C-Returns | J8: Missing quantity | K8: Good | L8: 1 | M8: 1 | N8: 1 | O8: 1 | P8: 179 | R8: 0 | S8: 179
A9: 45695 | B9: 45708 | C9: ="Q" & CHOOSE(MONTH(Returns!$A9), "1", "1", "1", "2", "2", "2", "3", "3", "3", "4", "4", "4") & "_" & YEAR(Returns!$A9) -> Q1_2025 | D9: Gujarat | E9: Amazon | F9: MFN | G9: Zody Diaper | H9: ZODY DIAPER - NVYBLU | I9: Rejected | J9: UND-UNKNOWN | K9: Box Damaged | L9: 1 | M9: 1 | N9: 1 | O9: 1 | P9: 284 | R9: 70.36 | S9: 284
A10: 45695 | B10: 45712 | C10: ="Q" & CHOOSE(MONTH(Returns!$A10), "1", "1", "1", "2", "2", "2", "3", "3", "3", "4", "4", "4") & "_" & YEAR(Returns!$A10) -> Q1_2025 | D10: West Bengal | E10: Amazon | F10: MFN | G10: Diaper Pad | H10: DIAPER PAD-5PCS | I10: C-Returns | J10: UND-UNKNOWN | K10: Product Mismatch | L10: 1 | M10: 1 | N10: 0 | O10: 5 | P10: 419 | R10: 265.93 | S10: 414
A11: 45691 | B11: 45710 | C11: ="Q" & CHOOSE(MONTH(Returns!$A11), "1", "1", "1", "2", "2", "2", "3", "3", "3", "4", "4", "4") & "_" & YEAR(Returns!$A11) -> Q1_2025 | D11: Goa | E11: Amazon | F11: MFN | G11: Diaper Pad | H11: DIAPER PAD-5PCS | I11: C-Returns | J11: CR-QUALITY_UNACCEPTABLE | K11: Damaged | L11: 1 | M11: 1 | N11: 0 | O11: 5 | P11: 399 | R11: 235.53 | S11: 399
A12: 45707 | B12: 45723 | C12: ="Q" & CHOOSE(MONTH(Returns!$A12), "1", "1", "1", "2", "2", "2", "3", "3", "3", "4", "4", "4") & "_" & YEAR(Returns!$A12) -> Q1_2025 | D12: Punjab | E12: Amazon | F12: MFN | G12: Diaper Pad | H12: DIAPER PAD-5PCS | I12: Rejected | J12: UND-UNKNOWN | K12: Good | L12: 1 | M12: 1 | N12: 5 | O12: 5 | P12: 479 | Q12: 5 | R12: 0 | S12: 479
A13: 45706 | B13: 45723 | C13: ="Q" & CHOOSE(MONTH(Returns!$A13), "1", "1", "1", "2", "2", "2", "3", "3", "3", "4", "4", "4") & "_" & YEAR(Returns!$A13) -> Q1_2025 | D13: Tamil Nadu | E13: Amazon | F13: MFN | G13: Jabala Wings | H13: DIAPER PAD-5PCS | I13: C-Returns | J13: AMZ-PG-APP-TOO-SMALL | K13: Good | L13: 1 | M13: 1 | N13: 5 | O13: 5 | P13: 299 | Q13: 5 | R13: 0 | S13: 294
A14: 45705 | B14: 45719 | C14: ="Q" & CHOOSE(MONTH(Returns!$A14), "1", "1", "1", "2", "2", "2", "3", "3", "3", "4", "4", "4") & "_" & YEAR(Returns!$A14) -> Q1_2025 | D14: West Bengal | E14: Amazon | F14: MFN | G14: Diaper Pad | H14: DIAPER PAD-5PCS | I14: Rejected | J14: UND-UNKNOWN | K14: Good | L14: 1 | M14: 1 | N14: 3 | O14: 3 | P14: 294 | Q14: 3 | R14: 0 | S14: 294
A15: 45703 | B15: 45719 | C15: ="Q" & CHOOSE(MONTH(Returns!$A15), "1", "1", "1", "2", "2", "2", "3", "3", "3", "4", "4", "4") & "_" & YEAR(Returns!$A15) -> Q1_2025 | D15: Haryana | E15: Amazon | F15: MFN | G15: Diaper Pad | H15: DIAPER PAD-5PCS | I15: Rejected | J15: UND-UNKNOWN | K15: Good | L15: 1 | M15: 1 | N15: 2 | O15: 2 | P15: 245 | Q15: 2 | R15: 0 | S15: 245
A16: 45710 | B16: 45724 | C16: ="Q" & CHOOSE(MONTH(Returns!$A16), "1", "1", "1", "2", "2", "2", "3", "3", "3", "4", "4", "4") & "_" & YEAR(Returns!$A16) -> Q1_2025 | D16: Delhi | E16: Amazon | F16: MFN | G16: Diaper Pad | H16: DIAPER PAD-3PCS | I16: Rejected | J16: UND-UNKNOWN | K16: Good | L16: 1 | M16: 1 | N16: 3 | O16: 3 | P16: 329 | Q16: 3 | R16: 0 | S16: 329
A17: 45705 | B17: 45715 | C17: ="Q" & CHOOSE(MONTH(Returns!$A17), "1", "1", "1", "2", "2", "2", "3", "3", "3", "4", "4", "4") & "_" & YEAR(Returns!$A17) -> Q1_2025 | D17: Tamil Nadu | E17: Amazon | F17: MFN | G17: Diaper Pad | H17: DIAPER PAD-3PCS | I17: Rejected | J17: UND-UNKNOWN | K17: Good | L17: 1 | M17: 1 | N17: 3 | O17: 3 | P17: 314 | Q17: 3 | R17: 0 | S17: 314
A18: 45703 | B18: 45719 | C18: ="Q" & CHOOSE(MONTH(Returns!$A18), "1", "1", "1", "2", "2", "2", "3", "3", "3", "4", "4", "4") & "_" & YEAR(Returns!$A18) -> Q1_2025 | D18: Maharashtra | E18: Amazon | F18: MFN | G18: Jabala Wings | H18: JABALA WINGS-3PCS- 3-6M-S2 | I18: C-Returns | J18: UND-UNKNOWN | K18: Good | L18: 1 | M18: 1 | N18: 3 | O18: 3 | P18: 199 | Q18: 3 | R18: 0 | S18: 199
A19: 45715 | B19: 45731 | C19: ="Q" & CHOOSE(MONTH(Returns!$A19), "1", "1", "1", "2", "2", "2", "3", "3", "3", "4", "4", "4") & "_" & YEAR(Returns!$A19) -> Q1_2025 | D19: Kerala | E19: Amazon | F19: MFN | G19: Diaper Pad | H19: DIAPER PAD-5PCS | I19: C-Returns | J19: CR-SWITCHEROO | K19: Product Mismatch | L19: 2 | M19: 2 | N19: 8 | O19: 10 | P19: 968.6 | Q19: 0 | R19: 0 | S19: 0
A20: 45733 | B20: 45743 | C20: ="Q" & CHOOSE(MONTH(Returns!$A20), "1", "1", "1", "2", "2", "2", "3", "3", "3", "4", "4", "4") & "_" & YEAR(Returns!$A20) -> Q1_2025 | D20: Tamil Nadu | E20: Amazon | F20: MFN | G20: Diaper Pad | H20: DIAPER PAD-3PCS | I20: Rejected | J20: UND-UNKNOWN | K20: Good | L20: 1 | M20: 1 | N20: 3 | O20: 3 | P20: 369 | Q20: 3 | R20: 0 | S20: 369
A21: 45728 | B21: 45743 | C21: ="Q" & CHOOSE(MONTH(Returns!$A21), "1", "1", "1", "2", "2", "2", "3", "3", "3", "4", "4", "4") & "_" & YEAR(Returns!$A21) -> Q1_2025 | D21: Madhya Pradesh | E21: Amazon | F21: MFN | G21: Diaper Pad | H21: DIAPER PAD-3PCS | I21: Rejected | J21: UND-UNKNOWN | K21: Good | L21: 1 | M21: 1 | N21: 3 | O21: 3 | P21: 369 | Q21: 3 | R21: 0 | S21: 369
A22: 45721 | B22: 45734 | C22: ="Q" & CHOOSE(MONTH(Returns!$A22), "1", "1", "1", "2", "2", "2", "3", "3", "3", "4", "4", "4") & "_" & YEAR(Returns!$A22) -> Q1_2025 | D22: Tamil Nadu | E22: Amazon | F22: MFN | G22: Jabala Wings | H22: JABALA WINGS-5PCS- 3-6M-S1 | I22: C-Returns | J22: AMZ-PG-APP-TOO-SMALL | K22: Good | L22: 1 | M22: 1 | N22: 5 | O22: 5 | P22: 399 | Q22: 5 | R22: 0 | S22: 399
A23: 45727 | B23: 45742 | C23: ="Q" & CHOOSE(MONTH(Returns!$A23), "1", "1", "1", "2", "2", "2", "3", "3", "3", "4", "4", "4") & "_" & YEAR(Returns!$A23) -> Q1_2025 | D23: Telangana | E23: Amazon | F23: MFN | G23: Jabala Wings | H23: JABALA WINGS-6PCS- 3-6M-S1 | I23: C-Returns | J23: AMZ-PG-APP-TOO-SMALL | K23: Good | L23: 1 | M23: 1 | N23: 6 | O23: 6 | P23: 449 | Q23: 6 | R23: 0 | S23: 449
... A27: 45748 | B27: 45755 | C27: ="Q" & CHOOSE(MONTH(Returns!$A27), "1", "1", "1", "2", "2", "2", "3", "3", "3", "4", "4", "4") & "_" & YEAR(Returns!$A27) -> Q2_2025 | D27: Tamil Nadu | E27: Amazon | F27: MFN | G27: Window Cradle Stand | H27: WND CRADLE STAND-1M-GRP | I27: Rejected | J27: UND-UNKNOWN | K27: Damaged | L27: 1 | M27: 1 | N27: 1 | O27: 1 | P27: 949 | Q27: 0 | R27: 0 | S27: 949
C28: ="Q" & CHOOSE(MONTH(Returns!$A28), "1", "1", "1", "2", "2", "2", "3", "3", "3", "4", "4", "4") & "_" & YEAR(Returns!$A28) -> Q1_1900
C29: ="Q" & CHOOSE(MONTH(Returns!$A29), "1", "1", "1", "2", "2", "2", "3", "3", "3", "4", "4", "4") & "_" & YEAR(Returns!$A29) -> Q1_1900
C30: ="Q" & CHOOSE(MONTH(Returns!$A30), "1", "1", "1", "2", "2", "2", "3", "3", "3", "4", "4", "4") & "_" & YEAR(Returns!$A30) -> Q1_1900
C31: ="Q" & CHOOSE(MONTH(Returns!$A31), "1", "1", "1", "2", "2", "2", "3", "3", "3", "4", "4", "4") & "_" & YEAR(Returns!$A31) -> Q1_1900
C32: ="Q" & CHOOSE(MONTH(Returns!$A32), "1", "1", "1", "2", "2", "2", "3", "3", "3", "4", "4", "4") & "_" & YEAR(Returns!$A32) -> Q1_1900
C33: ="Q" & CHOOSE(MONTH(Returns!$A33), "1", "1", "1", "2", "2", "2", "3", "3", "3", "4", "4", "4") & "_" & YEAR(Returns!$A33) -> Q1_1900
C34: ="Q" & CHOOSE(MONTH(Returns!$A34), "1", "1", "1", "2", "2", "2", "3", "3", "3", "4", "4", "4") & "_" & YEAR(Returns!$A34) -> Q1_1900
C35: ="Q" & CHOOSE(MONTH(Returns!$A35), "1", "1", "1", "2", "2", "2", "3", "3", "3", "4", "4", "4") & "_" & YEAR(Returns!$A35) -> Q1_1900
C36: ="Q" & CHOOSE(MONTH(Returns!$A36), "1", "1", "1", "2", "2", "2", "3", "3", "3", "4", "4", "4") & "_" & YEAR(Returns!$A36) -> Q1_1900
C37: ="Q" & CHOOSE(MONTH(Returns!$A37), "1", "1", "1", "2", "2", "2", "3", "3", "3", "4", "4", "4") & "_" & YEAR(Returns!$A37) -> Q1_1900
C38: ="Q" & CHOOSE(MONTH(Returns!$A38), "1", "1", "1", "2", "2", "2", "3", "3", "3", "4", "4", "4") & "_" & YEAR(Returns!$A38) -> Q1_1900
C39: ="Q" & CHOOSE(MONTH(Returns!$A39), "1", "1", "1", "2", "2", "2", "3", "3", "3", "4", "4", "4") & "_" & YEAR(Returns!$A39) -> Q1_1900
... C149: ="Q" & CHOOSE(MONTH(Returns!$A149), "1", "1", "1", "2", "2", "2", "3", "3", "3", "4", "4", "4") & "_" & YEAR(Returns!$A149) -> Q1_1900

Sheet Inventory
A1: Item Name | B1: Initial Qty | C1: Added Qty | D1: Review Return | E1: Sold Qty | F1: Return Qty | G1: Transferred Qty | H1: Remaining Qty | I1: Total Qty | J1: Total Pack of
A2: Zody Diaper | B2: 24 | C2: =SUMIFS(Added_Stock!C:C, Added_Stock!B:B, A2, Added_Stock!D:D, "Added") -> 237 | D2: 3 | E2: =SUMIF(Sales!G:G, A2, Sales!L:L) -> 248 | F2: =SUMIF(Returns!G:G, A2, Returns!N:N) -> 3 | G2: =SUMIFS(Added_Stock!C:C, Added_Stock!B:B, Inventory!$A2, Added_Stock!D:D, "Transferred") -> 6 | H2: =B2 + C2 + D2 + Inventory!$F2- E2 - G2 -> 13 | I2: =SUM(Inventory!$E2+Inventory!$H2) -> 261 | J2: =Inventory!$I2*1 -> 261
A3: Diaper Pad | B3: 18 | C3: =SUMIFS(Added_Stock!C:C, Added_Stock!B:B, A3, Added_Stock!D:D, "Added") -> 426 | D3: 0 | E3: =SUMIF(Sales!G:G, A3, Sales!L:L) -> 975 | F3: =SUMIF(Returns!G:G, A3, Returns!N:N) -> 30 | G3: =SUMIFS(Added_Stock!C:C, Added_Stock!B:B, Inventory!$A3, Added_Stock!D:D, "Transferred") -> 0 | H3: =B3 + C3 + D3 + Inventory!$F3- E3 - G3 -> -501 | I3: =SUM(Inventory!$E3+Inventory!$H3) -> 474 | J3: =Inventory!$I3/3 -> 158
A4: Jabala Mist | B4: 24 | C4: =SUMIFS(Added_Stock!C:C, Added_Stock!B:B, A4, Added_Stock!D:D, "Added") -> 6 | D4: 0 | E4: =SUMIF(Sales!G:G, A4, Sales!L:L) -> 24 | F4: =SUMIF(Returns!G:G, A4, Returns!N:N) -> 0 | G4: =SUMIFS(Added_Stock!C:C, Added_Stock!B:B, Inventory!$A4, Added_Stock!D:D, "Transferred") -> 0 | H4: =B4 + C4 + D4 + Inventory!$F4- E4 - G4 -> 6 | I4: =SUM(Inventory!$E4+Inventory!$H4) -> 30 | J4: =Inventory!$I4/6 -> 5
A5: Feeding Bed | B5: 13 | C5: =SUMIFS(Added_Stock!C:C, Added_Stock!B:B, A5, Added_Stock!D:D, "Added") -> 7 | D5: 0 | E5: =SUMIF(Sales!G:G, A5, Sales!L:L) -> 10 | F5: =SUMIF(Returns!G:G, A5, Returns!N:N) -> 0 | G5: =SUMIFS(Added_Stock!C:C, Added_Stock!B:B, Inventory!$A5, Added_Stock!D:D, "Transferred") -> 9 | H5: =B5 + C5 + D5 + Inventory!$F5- E5 - G5 -> 1 | I5: =SUM(Inventory!$E5+Inventory!$H5) -> 11 | J5: =Inventory!$I5*1 -> 11
A6: Jabala Rain | B6: 15 | C6: =SUMIFS(Added_Stock!C:C, Added_Stock!B:B, A6, Added_Stock!D:D, "Added") -> 0 | D6: 0 | E6: =SUMIF(Sales!G:G, A6, Sales!L:L) -> 10 | F6: =SUMIF(Returns!G:G, A6, Returns!N:N) -> 0 | G6: =SUMIFS(Added_Stock!C:C, Added_Stock!B:B, Inventory!$A6, Added_Stock!D:D, "Transferred") -> 0 | H6: =B6 + C6 + D6 + Inventory!$F6- E6 - G6 -> 5 | I6: =SUM(Inventory!$E6+Inventory!$H6) -> 15 | J6: =Inventory!$I6/3 -> 5
A7: Jabala Wings | B7: 18 | C7: =SUMIFS(Added_Stock!C:C, Added_Stock!B:B, A7, Added_Stock!D:D, "Added") -> 258 | D7: 0 | E7: =SUMIF(Sales!G:G, A7, Sales!L:L) -> 304 | F7: =SUMIF(Returns!G:G, A7, Returns!N:N) -> 31 | G7: =SUMIFS(Added_Stock!C:C, Added_Stock!B:B, Inventory!$A7, Added_Stock!D:D, "Transferred") -> 0 | H7: =B7 + C7 + D7 + Inventory!$F7- E7 - G7 -> 3 | I7: =SUM(Inventory!$E7+Inventory!$H7) -> 307 | J7: =Inventory!$I7/3 -> 102.33333
A8: Dry Sheet (S) | B8: 12 | C8: =SUMIFS(Added_Stock!C:C, Added_Stock!B:B, A8, Added_Stock!D:D, "Added") -> 0 | D8: 0 | E8: =SUMIF(Sales!G:G, A8, Sales!L:L) -> 14 | F8: =SUMIF(Returns!G:G, A8, Returns!N:N) -> 3 | G8: =SUMIFS(Added_Stock!C:C, Added_Stock!B:B, Inventory!$A8, Added_Stock!D:D, "Transferred") -> 0 | H8: =B8 + C8 + D8 + Inventory!$F8- E8 - G8 -> 1 | I8: =SUM(Inventory!$E8+Inventory!$H8) -> 15 | J8: =Inventory!$I8*1 -> 15
A9: Dry Sheet (M) | B9: 6 | C9: =SUMIFS(Added_Stock!C:C, Added_Stock!B:B, A9, Added_Stock!D:D, "Added") -> 0 | D9: 0 | E9: =SUMIF(Sales!G:G, A9, Sales!L:L) -> 0 | F9: =SUMIF(Returns!G:G, A9, Returns!N:N) -> 0 | G9: =SUMIFS(Added_Stock!C:C, Added_Stock!B:B, Inventory!$A9, Added_Stock!D:D, "Transferred") -> 0 | H9: =B9 + C9 + D9 + Inventory!$F9- E9 - G9 -> 6 | I9: =SUM(Inventory!$E9+Inventory!$H9) -> 6 | J9: =Inventory!$I9*1 -> 6
A10: Dry Sheet (L) | B10: 4 | C10: =SUMIFS(Added_Stock!C:C, Added_Stock!B:B, A10, Added_Stock!D:D, "Added") -> 0 | D10: 0 | E10: =SUMIF(Sales!G:G, A10, Sales!L:L) -> 0 | F10: =SUMIF(Returns!G:G, A10, Returns!N:N) -> 0 | G10: =SUMIFS(Added_Stock!C:C, Added_Stock!B:B, Inventory!$A10, Added_Stock!D:D, "Transferred") -> 0 | H10: =B10 + C10 + D10 + Inventory!$F10- E10 - G10 -> 4 | I10: =SUM(Inventory!$E10+Inventory!$H10) -> 4 | J10: =Inventory!$I10*1 -> 4
A11: Kang De Bed-PRO | B11: 1 | C11: =SUMIFS(Added_Stock!C:C, Added_Stock!B:B, A11, Added_Stock!D:D, "Added") -> 7 | D11: 0 | E11: =SUMIF(Sales!G:G, A11, Sales!L:L) -> 3 | F11: =SUMIF(Returns!G:G, A11, Returns!N:N) -> 0 | G11: =SUMIFS(Added_Stock!C:C, Added_Stock!B:B, Inventory!$A11, Added_Stock!D:D, "Transferred") -> 0 | H11: =B11 + C11 + D11 + Inventory!$F11- E11 - G11 -> 5 | I11: =SUM(Inventory!$E11+Inventory!$H11) -> 8 | J11: =Inventory!$I11*1 -> 8
A12: Kang De Bed | B12: 1 | C12: =SUMIFS(Added_Stock!C:C, Added_Stock!B:B, A12, Added_Stock!D:D, "Added") -> 9 | D12: 0 | E12: =SUMIF(Sales!G:G, A12, Sales!L:L) -> 2 | F12: =SUMIF(Returns!G:G, A12, Returns!N:N) -> 1 | G12: =SUMIFS(Added_Stock!C:C, Added_Stock!B:B, Inventory!$A12, Added_Stock!D:D, "Transferred") -> 2 | H12: =B12 + C12 + D12 + Inventory!$F12- E12 - G12 -> 7 | I12: =SUM(Inventory!$E12+Inventory!$H12) -> 9 | J12: =Inventory!$I12*1 -> 9
A13: Baby Pillow | B13: 10 | C13: =SUMIFS(Added_Stock!C:C, Added_Stock!B:B, A13, Added_Stock!D:D, "Added") -> 0 | D13: 0 | E13: =SUMIF(Sales!G:G, A13, Sales!L:L) -> 11 | F13: =SUMIF(Returns!G:G, A13, Returns!N:N) -> 0 | G13: =SUMIFS(Added_Stock!C:C, Added_Stock!B:B, Inventory!$A13, Added_Stock!D:D, "Transferred") -> 0 | H13: =B13 + C13 + D13 + Inventory!$F13- E13 - G13 -> -1 | I13: =SUM(Inventory!$E13+Inventory!$H13) -> 10 | J13: =Inventory!$I13*1 -> 10
A14: MICO Baby Pillow | B14: 20 | C14: =SUMIFS(Added_Stock!C:C, Added_Stock!B:B, A14, Added_Stock!D:D, "Added") -> 0 | D14: 0 | E14: =SUMIF(Sales!G:G, A14, Sales!L:L) -> 0 | F14: =SUMIF(Returns!G:G, A14, Returns!N:N) -> 0 | G14: =SUMIFS(Added_Stock!C:C, Added_Stock!B:B, Inventory!$A14, Added_Stock!D:D, "Transferred") -> 0 | H14: =B14 + C14 + D14 + Inventory!$F14- E14 - G14 -> 20 | I14: =SUM(Inventory!$E14+Inventory!$H14) -> 20 | J14: =Inventory!$I14*1 -> 20
A15: Window Cradle Stand | B15: 5 | C15: =SUMIFS(Added_Stock!C:C, Added_Stock!B:B, A15, Added_Stock!D:D, "Added") -> 53 | D15: 0 | E15: =SUMIF(Sales!G:G, A15, Sales!L:L) -> 87 | F15: =SUMIF(Returns!G:G, A15, Returns!N:N) -> 3 | G15: =SUMIFS(Added_Stock!C:C, Added_Stock!B:B, Inventory!$A15, Added_Stock!D:D, "Transferred") -> 5 | H15: =B15 + C15 + D15 + Inventory!$F15- E15 - G15 -> -31 | I15: =SUM(Inventory!$E15+Inventory!$H15) -> 56 | J15: =Inventory!$I15*1 -> 56
A16: Pluto Bed Cradle | B16: 5 | C16: =SUMIFS(Added_Stock!C:C, Added_Stock!B:B, A16, Added_Stock!D:D, "Added") -> 0 | D16: 0 | E16: =SUMIF(Sales!G:G, A16, Sales!L:L) -> 0 | F16: =SUMIF(Returns!G:G, A16, Returns!N:N) -> 0 | G16: =SUMIFS(Added_Stock!C:C, Added_Stock!B:B, Inventory!$A16, Added_Stock!D:D, "Transferred") -> 0 | H16: =B16 + C16 + D16 + Inventory!$F16- E16 - G16 -> 5 | I16: =SUM(Inventory!$E16+Inventory!$H16) -> 5 | J16: =Inventory!$I16*1 -> 5
A17: Hanger Plus | B17: 25 | C17: =SUMIFS(Added_Stock!C:C, Added_Stock!B:B, A17, Added_Stock!D:D, "Added") -> 0 | D17: 0 | E17: =SUMIF(Sales!G:G, A17, Sales!L:L) -> 46 | F17: =SUMIF(Returns!G:G, A17, Returns!N:N) -> 0 | G17: =SUMIFS(Added_Stock!C:C, Added_Stock!B:B, Inventory!$A17, Added_Stock!D:D, "Transferred") -> 0 | H17: =B17 + C17 + D17 + Inventory!$F17- E17 - G17 -> -21 | I17: =SUM(Inventory!$E17+Inventory!$H17) -> 25 | J17: =Inventory!$I17*1 -> 25
A18: Gold Cradle Cloth | B18: 2 | C18: =SUMIFS(Added_Stock!C:C, Added_Stock!B:B, A18, Added_Stock!D:D, "Added") -> 0 | D18: 0 | E18: =SUMIF(Sales!G:G, A18, Sales!L:L) -> 0 | F18: =SUMIF(Returns!G:G, A18, Returns!N:N) -> 0 | G18: =SUMIFS(Added_Stock!C:C, Added_Stock!B:B, Inventory!$A18, Added_Stock!D:D, "Transferred") -> 0 | H18: =B18 + C18 + D18 + Inventory!$F18- E18 - G18 -> 2 | I18: =SUM(Inventory!$E18+Inventory!$H18) -> 2 | J18: =Inventory!$I18*1 -> 2
A19: Bliss Bed Cover 6.25X6 | B19: 2 | C19: =SUMIFS(Added_Stock!C:C, Added_Stock!B:B, A19, Added_Stock!D:D, "Added") -> 0 | D19: 0 | E19: =SUMIF(Sales!G:G, A19, Sales!L:L) -> 0 | F19: =SUMIF(Returns!G:G, A19, Returns!N:N) -> 0 | G19: =SUMIFS(Added_Stock!C:C, Added_Stock!B:B, Inventory!$A19, Added_Stock!D:D, "Transferred") -> 0 | H19: =B19 + C19 + D19 + Inventory!$F19- E19 - G19 -> 2 | I19: =SUM(Inventory!$E19+Inventory!$H19) -> 2 | J19: =Inventory!$I19*1 -> 2
... A22: Aroz Socks Size 1 | B22: 1 | C22: =SUMIFS(Added_Stock!C:C, Added_Stock!B:B, A22, Added_Stock!D:D, "Added") -> 5 | D22: 0 | E22: =SUMIF(Sales!G:G, A22, Sales!L:L) -> 12 | F22: =SUMIF(Returns!G:G, A22, Returns!N:N) -> 0 | G22: =SUMIFS(Added_Stock!C:C, Added_Stock!B:B, Inventory!$A22, Added_Stock!D:D, "Transferred") -> 0 | H22: =B22 + C22 + D22 + Inventory!$F22- E22 - G22 -> -6 | I22: =SUM(Inventory!$E22+Inventory!$H22) -> 6 | J22: =Inventory!$I22*1 -> 6

Sheet Disbursements
A1: Date | B1: Payement Type | C1: Platforms | D1: Amount
A2: 45732 | B2: Electronic Transaction | C2: Amazon | D2: 7112.44
A3: 45739 | B3: Electronic Transaction | C3: Amazon | D3: 10964.16
A4: 45714 | B4: COD Transaction | C4: Amazon | D4: 1922.53
A5: 45721 | B5: COD Transaction | C5: Amazon | D5: 1678.61
A6: 45728 | B6: COD Transaction | C6: Amazon | D6: 5365.62
A7: 45735 | B7: COD Transaction | C7: Amazon | D7: 7432.46
A8: 45742 | B8: COD Transaction | C8: Amazon | D8: 6011.15
A9: 45745 | B9: Electronic Transaction | C9: Amazon | D9: 14893.61
A10: 45701 | B10: N/A | C10: meesho | D10: 169.3
A11: 45701 | B11: N/A | C11: meesho | D11: 0
A12: 45701 | B12: N/A | C12: meesho | D12: 1409.05
A13: 45702 | B13: N/A | C13: meesho | D13: 134.26
... A35: 45801 | B35: Electronic Transaction | C35: Amazon | D35: 9249.02

Sheet Added_Stock
A1: Date | B1: Item Name | C1: Added/Transferred Quantity | D1: Type
A2: 45686 | B2: Zody Diaper | C2: 23 | D2: Added
A3: 45687 | B3: Feeding Bed | C3: 6 | D3: Added
A4: 45688 | B4: Feeding Bed | C4: 1 | D4: Transferred
A5: 45688 | B5: Feeding Bed | C5: 1 | D5: Added
A6: 45688 | B6: Diaper Pad | C6: 27 | D6: Added
A7: 45689 | B7: Jabala Wings | C7: 3 | D7: Added
A8: 45689 | B8: Jabala Mist | C8: 6 | D8: Added
A9: 45689 | B9: Jabala Wings | C9: 3 | D9: Added
A10: 45691 | B10: Zody Diaper | C10: 5 | D10: Transferred
A11: 45691 | B11: Zody Diaper | C11: 7 | D11: Added
A12: 45691 | B12: Zody Diaper | C12: 1 | D12: Added
A13: 45692 | B13: Jabala Wings | C13: 24 | D13: Added
... A43: 45723 | B43: Zody Diaper | C43: 60 | D43: Added
A252: Total | C252: =SUBTOTAL(109,Added_Stock!$C$2:$C$251) -> 1045 | D252: =SUBTOTAL(103,Added_Stock!$D$2:$D$251) -> 42

Sheet Target_List
A1: Period | B1: Year | C1: Currency | D1: TargetAmount
A2: Quarter_1 | B2: 2025 | C2: INR
A3: Quarter_2 | B3: 2025 | C3: INR | D3: 200000
A4: Quarter_3 | B4: 2025 | C4: INR
A5: Quarter_4 | B5: 2025 | C5: INR

Sheet Review Purchase
A1: Order Date | B1: Platform | C1: Order ID | D1: ASIN | E1: Product | F1: Keywords | G1: Buyer Name | H1: Amount | I1: Invoice | J1: Status
A2: 45764 | B2: Amazon | C2: 403-4960461-5443535 | D2: B0DWDGWR8X | E2: Diaper Pad | F2: Cloth Diaper Pad | G2: Shikha Sharma | H2: 264 | I2: Submitted | J2: Purchased
A3: 45764 | B3: Amazon | C3: 404-2972091-2841918 | D3: B0DWDGWR8X | E3: Diaper Pad | F3: Cloth Diaper Pad | G3: Lijo Jose | H3: 276 | I3: Submitted | J3: Reviewd
A4: 45757 | B4: Amazon | C4: 403-3883286-9205166 | D4: B0DY4CTFRB | E4: Cradle Spring with Hanger | F4: Cradle Hanger | G4: Shikha Sharma | H4: 497 | I4: Submitted | J4: Reviewd
A5: 45759 | B5: meesho | C5: 142935359852546368_1 | D5: 8E9F1H3I4 | E5: Dry Sheet (S) | F5: Link | G5: Naji | H5: 158 | I5: Not Submitted | J5: Reviewd
A6: 45770 | B6: meesho | C6: 146487789684097152_1 | D6: 9D8F3A4C5 | E6: Alina | F6: Link | G6: Jaseel | H6: 223 | I6: Submitted | J6: Purchased

Sheet Data_Validation
A1: Fulfilled by | B1: Platform | C1: Location | D1: Currency | E1: Product Type | F1: Product ID | G1: Product Name | H1: Order_Type | I1: Return_Reason | J1: Return_Type | K1: Period | L1: Stock Transfer Type | M1: Product_Condition | N1: Rating | O1: Review Length | P1: Disbursement_Type | Q1: Sentiment | R1: Review Status | S1: Invoice
A2: MFN | B2: Amazon | C2: Andhra Pradesh | D2: INR | E2: Single | F2: ZODY DIAPER - NVYBLU | G2: Zody Diaper | H2: Review Purchase | J2: Rejected | K2: Quarter_1 | L2: Added | M2: Good | N2: 1 | O2: Short | P2: COD Transaction | Q2: Positive | R2: Purchased | S2: Submitted
A3: FBA | B3: meesho | C3: Arunachal Pradesh | E3: Bundle | F3: ZODY DIAPER-2PCS | G3: Feeding Bed | H3: Organic | J3: C-Returns | K3: Quarter_2 | L3: Transferred | M3: Damaged | N3: 2 | O3: Long | P3: Electronic Transaction | Q3: Neutral | R3: Delivered | S3: Not Submitted
A4: Flex | B4: Myntra | C4: Assam | E4: MOQ | F4: ZODY DIAPER-2PCS-MC1+MC2 | G4: Jabala Mist | H4: Free | K4: Quarter_3 | M4: Box Damaged | N4: 3 | P4: N/A | Q4: Negative | R4: Reviewd
A5: FBF | B5: IndiaMART | C5: Bihar | F5: ZODY DIAPER-2PCS-MC3+MC4 | G5: Diaper Pad | H5: Exchange | K5: Quarter_4 | M5: Product Mismatch | N5: 4
B6: Whatsapp | C6: Chhattisgarh | F6: ZODY DIAPER-MC7 | G6: Jabala Rain | N6: 5
B7: Flipkart | C7: Delhi | F7: ZODY DIAPER-MC6 | G7: Jabala Wings
C8: Goa | F8: ZODY DIAPER-MC5 | G8: Dry Sheet (L)
C9: Gujarat | F9: ZODY DIAPER-MC4 | G9: Dry Sheet (M)
C10: Haryana | F10: ZODY DIAPER-MC3 | G10: Dry Sheet (S)
C11: Himachal Pradesh | F11: ZODY DIAPER-MC2 | G11: Kang De Bed
C12: Jharkhand | F12: ZODY DIAPER-MC1 | G12: Kang De Bed-PRO
C13: Jammu and Kashmir | F13: ZODY DIAPER-5PCS | G13: Baby Pillow
C14: Karnataka | F14: ZODY DIAPER-3PCS-S1 | G14: MICO Baby Pillow
C15: Kerala | F15: ZODY DIAPER-3PCS-S2 | G15: Window Cradle Stand
C16: Madhya Pradesh | F16: DIAPER PAD-1PCS | G16: Pluto Bed Cradle
C17: Maharashtra | F17: DIAPER PAD-2PCS | G17: Hanger Plus
C18: Manipur | F18: DIAPER PAD-3PCS | G18: Gold Cradle Cloth
C19: Meghalaya | F19: DIAPER PAD-5PCS | G19: Bliss Bed Cover 6.25X6
... C31: West Bengal | F31: JABALA WINGS-5PCS- 0-3M-S1 | G31: Fionaya
C32: N/A | F32: JABALA WINGS-5PCS- 0-3M-S2
F33: DRY SHEET-SKY-S
F34: KANG DE BED-ROSE
F35: JABALA WINGS-5PCS- 0-3M-S1
F36: JABALA WINGS-5PCS- 3-6M-S1
F37: JABALA WINGS-3PCS- 3-6M-S2
F38: JABALA WINGS-3PCS- 0-3M-S2
F39: JABALA WINGS-3PCS- 3-6M-S1
F40: JABALA WINGS-6PCS- 0-3M-S2
F41: JABALA WINGS-3PCS-S1
F42: JABALA WINGS-6PCS- 3-6M-S1
F43: JABALA WINGS-6PCS- 3-6M-S2
F44: JABALA WINGS-6PCS- 0-3M-S1
... F62: FIONAYA-PNK
